{
  "update_time": "2025-11-24",
  "articles": [
    {
      "title": "半日主力资金加仓国防军工板块，抛售有色金属板块",
      "link": "https://36kr.com/newsflashes/3566528942881927?f=rss",
      "date": "2025-11-24 11:52",
      "author": "36氪",
      "timestamp": 1763956366.0,
      "summary": "主力资金早间净流入国防军工、通信、建筑装饰等板块，净流出有色金属、电子、公用事业等板块。具体到个股来看，实达集团、中船防务、国风新材获净流入21.01亿元、12.15亿元、11.30亿元。净流出方面，中际旭创、平潭发展、易点天下遭抛售10.73亿元、8.73亿元、6.38亿元。（第一财经）",
      "source_url": "http://36kr.com",
      "category": "Blog"
    },
    {
      "title": "英国 DragonFire 激光武器精准击落 650 km/h 高速无人机，单次发射成本 10 英镑",
      "link": "https://www.ithome.com/0/899/707.htm",
      "date": "2025-11-24 11:51",
      "author": "IT之家",
      "timestamp": 1763956278.0,
      "summary": "IT之家 11 月 24 日消息，科技媒体 Tom's Hardware 今天（11 月 24 日）发布博文，报道称英国国防部的“龙火”（DragonFire）高能激光武器系统在最新测试中，成功击落时速高达 403 英里（约 650 公里）的高速无人机。该系统首次在英国实现跟踪与拦截超视距（abov",
      "source_url": "https://www.ithome.com/",
      "category": "Blog"
    },
    {
      "title": "智元发布灵心平台，可个性化定制机器人声音、性格、人设、记忆",
      "link": "https://www.ithome.com/0/899/706.htm",
      "date": "2025-11-24 11:49",
      "author": "IT之家",
      "timestamp": 1763956175.0,
      "summary": "IT之家 11 月 24 日消息，智元机器人今日宣布推出灵心平台，用户无需代码基础，即可通过拖拽点选定制机器人的声音、行为、人设、记忆并配置任务。该平台内置 30-40 款风格各异的现成音色，无论是温柔陪伴型、俏皮互动型，还是方言趣味型，用户均可自由选择；更支持“音色复刻”功能，上传一段录音，即可让",
      "source_url": "https://www.ithome.com/",
      "category": "Blog"
    },
    {
      "title": "智元机器人推出灵心平台",
      "link": "https://36kr.com/newsflashes/3566536002174088?f=rss",
      "date": "2025-11-24 11:48",
      "author": "36氪",
      "timestamp": 1763956082.0,
      "summary": "36氪获悉，智元机器人宣布正式推出灵心平台（LinkSoul），可为机器人自由配置声音、性格、行为与记忆，内置30-40款风格各异的现成音色。",
      "source_url": "http://36kr.com",
      "category": "Blog"
    },
    {
      "title": "极越汽车：App 离线及车辆远程控制功能已全部恢复正常",
      "link": "https://www.ithome.com/0/899/703.htm",
      "date": "2025-11-24 11:45",
      "author": "IT之家",
      "timestamp": 1763955929.0,
      "summary": "IT之家 11 月 24 日消息，11 月 23 日晚 22 时许，多位极越车主反馈，极越汽车出现突发网络故障，手机 App 端显示车辆处于“离线”状态，导致用户无法使用远程控制等关键功能。当晚，极越汽车官微回应称，技术团队已第一时间启动应急响应机制，全力进行问题排查与修复工作。随后在今天上午 9",
      "source_url": "https://www.ithome.com/",
      "category": "Blog"
    },
    {
      "title": "三亚机场2025年旅客吞吐量突破2000万人次",
      "link": "https://36kr.com/newsflashes/3566513820662659?f=rss",
      "date": "2025-11-24 11:44",
      "author": "36氪",
      "timestamp": 1763955861.0,
      "summary": "36氪获悉，据三亚发布消息，截至2025年11月23日，三亚凤凰国际机场2025年旅客吞吐量已突破2000万大关，累计保障运输起降122170架次，共计运送旅客2003.36万人次，同比分别增长7.30%、6.00%。",
      "source_url": "http://36kr.com",
      "category": "Blog"
    },
    {
      "title": "致敬 Xbox 360，NACON 发布 REVOLUTION X UNLIMITED 周年纪念版带屏手柄",
      "link": "https://www.ithome.com/0/899/702.htm",
      "date": "2025-11-24 11:41",
      "author": "IT之家",
      "timestamp": 1763955710.0,
      "summary": "IT之家 11 月 24 日消息，本月 22 日是微软 Xbox 360 游戏主机发售 20 周年，为庆祝这一时间节点，NACON 宣布为旗下 REVOLUTION X UNLIMITED 带屏手柄 / 控制器推出 Anniversary Edition 周年纪念版。REVOLUTION X UNL",
      "source_url": "https://www.ithome.com/",
      "category": "Blog"
    },
    {
      "title": "拓竹回应：新一轮融资消息不实",
      "link": "https://36kr.com/newsflashes/3566529820244864?f=rss",
      "date": "2025-11-24 11:41",
      "author": "36氪",
      "timestamp": 1763955704.0,
      "summary": "有媒体报道称，拓竹接近完成最新一轮融资，腾讯参投，公司估值或达100亿美元。拓竹科技回应称，该消息不属实。（21财经）",
      "source_url": "http://36kr.com",
      "category": "Blog"
    },
    {
      "title": "特斯拉：Model Y长续航全轮驱动版预计交付日期为8-13周",
      "link": "https://36kr.com/newsflashes/3566522899840133?f=rss",
      "date": "2025-11-24 11:40",
      "author": "36氪",
      "timestamp": 1763955638.0,
      "summary": "36氪获悉，特斯拉宣布Model Y长续航全轮驱动版预计交付日期更新为8-13周。",
      "source_url": "http://36kr.com",
      "category": "Blog"
    },
    {
      "title": "小米澎湃 OS 3 十一月升级汇总：超级小爱随心修图上线，更多应用接入超级岛",
      "link": "https://www.ithome.com/0/899/701.htm",
      "date": "2025-11-24 11:40",
      "author": "IT之家",
      "timestamp": 1763955632.0,
      "summary": "IT之家 11 月 24 日消息，小米今日公布澎湃 OS 3 十一月升级汇总，包括超级小爱随心修图、更多应用接入超级岛等等。IT之家整理部分内容如下：超级小爱随心修图上线在相册大图页选择照片，唤醒超级小爱后即可随心表达修图需求。无需专业技能，随便说，都能修更多应用通知登陆小米超级岛小米超级岛已适配小",
      "source_url": "https://www.ithome.com/",
      "category": "Blog"
    },
    {
      "title": "拓竹几近完成新一轮融资，大厂参投，估值或达100亿美金｜36氪独家",
      "link": "https://36kr.com/p/3566526394481543?f=rss",
      "date": "2025-11-24 11:39",
      "author": "36氪",
      "timestamp": 1763955542.0,
      "summary": "作者&nbsp;|&nbsp;张子怡\n  编辑&nbsp;|&nbsp;袁斯来 杨轩\n  近日，多位投资人及3D打印行业人士告诉硬氪，拓竹接近完成最新一轮融资，腾讯参投，公司估值或达100亿美金。\n  这次融资已有前兆。今年7月30日，拓竹与腾讯云达成全面合作，旗下3D模型平台MakerWorld将",
      "source_url": "http://36kr.com",
      "category": "Blog"
    },
    {
      "title": "社区悬赏 2000 美元，一个月修复联想笔记本 Linux 音频问题",
      "link": "https://www.ithome.com/0/899/699.htm",
      "date": "2025-11-24 11:36",
      "author": "IT之家",
      "timestamp": 1763955418.0,
      "summary": "IT之家 11 月 24 日消息，科技媒体 Tom's Hardware 昨日（11 月 23 日）发布博文，报道称因不满联想拯救者 Pro 7 游戏本（16IAX10H）在 Linux 系统下扬声器音效“尖锐沉闷”，用户 Nadim Kobeissi 于 10 月发起联合悬赏，开发者 Yakov",
      "source_url": "https://www.ithome.com/",
      "category": "Blog"
    },
    {
      "title": "消息称华为 Mate 80 Pro Max / RS 独享新一代超透亮灵珑屏，双层 OLED",
      "link": "https://www.ithome.com/0/899/698.htm",
      "date": "2025-11-24 11:36",
      "author": "IT之家",
      "timestamp": 1763955364.0,
      "summary": "IT之家 11 月 24 日消息，博主 @数码闲聊站 今日爆料，华为 Mate 80 Pro Max / RS 独享新一代超透亮灵珑屏，也就是双层 OLED，6.9\"1.5K LTPO 超大直屏，影像独享 50Mp 1/1.28\" 超大底超高动态主摄 + 双长焦，还有第二代红枫影像，PM 还上了全金",
      "source_url": "https://www.ithome.com/",
      "category": "Blog"
    },
    {
      "title": "Gartner最新报告：阿里云在生成式AI四大维度均列领导者象限",
      "link": "https://36kr.com/newsflashes/3566515520765064?f=rss",
      "date": "2025-11-24 11:35",
      "author": "36氪",
      "timestamp": 1763955308.0,
      "summary": "36氪获悉，国际市场研究机构Gartner发布4篇GenAI（生成式AI）技术创新指南系列报告，公布了GenAI云基础设施、GenAI工程、GenAI模型以及AI知识管理应用四大维度的新兴市场象限（Emerging Market Quadrant），阿里云在四大维度均位于新兴领导者象限，为入选全部四",
      "source_url": "http://36kr.com",
      "category": "Blog"
    },
    {
      "title": "一加 Ace 6T 手机外观细节公布：全新升级快捷键，丝绸玻璃、旗舰玻纤材质",
      "link": "https://www.ithome.com/0/899/697.htm",
      "date": "2025-11-24 11:31",
      "author": "IT之家",
      "timestamp": 1763955119.0,
      "summary": "IT之家 11 月 24 日消息，一加 Ace 6T 手机将于近期发布，官方今日公布了这款新机的外观设计细节。据介绍，这款新机配备「金属魔方」Deco（相机装饰），更小、更不突出，机身正面采用大直屏、超窄边设计。此外，该产品还全新升级「快捷键」：一键闪记声音与振动免打扰相机手电筒录音翻译截屏无操作材",
      "source_url": "https://www.ithome.com/",
      "category": "Blog"
    },
    {
      "title": "A股三大指数午间休盘集体下跌，工业富联盘中跌停",
      "link": "https://36kr.com/newsflashes/3566519794269060?f=rss",
      "date": "2025-11-24 11:31",
      "author": "36氪",
      "timestamp": 1763955092.0,
      "summary": "36氪获悉，A股三大指数午间休盘集体下跌，沪指跌0.34%，深成指跌0.59%，创业板指跌0.77%；消费电子、锂矿、半导体板块领跌，工业富联盘中跌停，天齐锂业、赣锋锂业跌超9%；航天军工、文化传媒板块涨幅居前，中天火箭涨停，晨曦航空、蓝色光标涨超8%。",
      "source_url": "http://36kr.com",
      "category": "Blog"
    },
    {
      "title": "廉价VPS服务器提供商RackNerd黑五促销开始 每月2TB流量服务器仅需10.6美元/年",
      "link": "https://www.landiannews.com/archives/111204.html",
      "date": "2025-11-24 11:28",
      "author": "蓝点网",
      "timestamp": 1763954929.0,
      "summary": "知名廉价 VPS 服务器提供商 RackNerd 日前已经上线黑色星期五特别活动，此次活动提供 5 款服务器， [&#8230;]",
      "source_url": "https://www.landiannews.com",
      "category": "Blog"
    },
    {
      "title": "季度同比扭亏为盈，斗鱼多元内容精细化运营战略现成效",
      "link": "https://36kr.com/p/3566500435803268?f=rss",
      "date": "2025-11-24 11:28",
      "author": "36氪",
      "timestamp": 1763954909.0,
      "summary": "2025年第三季度，斗鱼交出一份稳中有升、不乏亮点的业绩报告。\n  11月20日，斗鱼2025年第三季度未经审计财务报告显示，当季营收为8.99亿元。盈利能力持续向好，毛利润达1.16亿元，同比增长90.9%，毛利率为12.9%，净利润为1133万元，同比提升232.8%，调整后净利润为2314万元",
      "source_url": "http://36kr.com",
      "category": "Blog"
    },
    {
      "title": "沪深两市成交额突破1万亿元",
      "link": "https://36kr.com/newsflashes/3566514464619648?f=rss",
      "date": "2025-11-24 11:26",
      "author": "36氪",
      "timestamp": 1763954767.0,
      "summary": "36氪获悉，沪深两市成交额连续第122个交易日突破1万亿元。",
      "source_url": "http://36kr.com",
      "category": "Blog"
    },
    {
      "title": "特斯拉中国：Model Y 长续航全轮驱动版预计交付日期更新为 8-13 周",
      "link": "https://www.ithome.com/0/899/695.htm",
      "date": "2025-11-24 11:21",
      "author": "IT之家",
      "timestamp": 1763954466.0,
      "summary": "IT之家 11 月 24 日消息，特斯拉中国官博今日宣布，Model Y 长续航全轮驱动版预计交付日期更新为 8-13 周。即日起至 11 月 30 日（含）前参加引荐奖励活动下单，可享 8000 元车漆选装礼金，下单指定版本车型，可申请限时 5 年 0 息金融方案。特斯拉焕新 Model Y 于今",
      "source_url": "https://www.ithome.com/",
      "category": "Blog"
    },
    {
      "title": "亿纬锂能拟与 SK On 进行股权置换，进一步强化资源整合",
      "link": "https://www.ithome.com/0/899/693.htm",
      "date": "2025-11-24 11:19",
      "author": "IT之家",
      "timestamp": 1763954381.0,
      "summary": "IT之家 11 月 24 日消息，亿纬锂能本月 20 日发布公告，拟与韩国电池企业 SK On 进行股权置换。此举旨在化解交叉持股关系，进一步强化资源整合。亿纬锂能旗下包含一家子公司亿纬动力，亿纬动力又派生出亿纬锂能的两家孙公司亿纬动力香港、亿纬集能。SK On 在中国拥有一家名为 SK 新能源（江",
      "source_url": "https://www.ithome.com/",
      "category": "Blog"
    },
    {
      "title": "IPv5 去哪了？“史前版远程会议”协议，被技术进步淘汰",
      "link": "https://www.ithome.com/0/899/692.htm",
      "date": "2025-11-24 11:18",
      "author": "IT之家",
      "timestamp": 1763954303.0,
      "summary": "IT之家 11 月 24 日消息，科技媒体 Tom's Hardware 昨日（11 月 23 日）发布博文，报道称互联网发展史上有一个著名的断层：我们从 IPv4 直接跨越到了 IPv6，中间的“5”去哪了？其实，IPv5 并非像跳过 Windows 9 进入 Windows 10 那样的营销策略",
      "source_url": "https://www.ithome.com/",
      "category": "Blog"
    },
    {
      "title": "达特茅斯学院开发新型 AI 工具：可伪装人类完成问卷，还能破解 99.8% 检测",
      "link": "https://www.ithome.com/0/899/691.htm",
      "date": "2025-11-24 11:17",
      "author": "IT之家",
      "timestamp": 1763954256.0,
      "summary": "IT之家 11 月 24 日消息，据 404 Media 报道，达特茅斯学院政府学副教授、极化研究实验室负责人肖恩・韦斯特伍德日前在《美国国家科学院院刊》（PNAS）上发表的一项新研究指出，在线调查研究作为许多科学研究中数据收集的基础方法，正面临着大语言模型带来的严重威胁。韦斯特伍德开发了一款名为“",
      "source_url": "https://www.ithome.com/",
      "category": "Blog"
    },
    {
      "title": "比亚迪仰望汽车全系 OTA 升级，U8L 新增平行横移功能",
      "link": "https://www.ithome.com/0/899/690.htm",
      "date": "2025-11-24 11:13",
      "author": "IT之家",
      "timestamp": 1763953999.0,
      "summary": "IT之家 11 月 24 日消息，比亚迪仰望汽车今日宣布全系 OTA 升级，具体车型包含仰望 U7、仰望 U8、仰望 U9、仰望 U8L。IT之家整理如下：仰望 U7、U8 共同新增 4 项功能新增荣耀车联：适配荣耀 Magic 系列机型，支持导航流转、应用流转等功能。新增比亚迪 App 百变主题自",
      "source_url": "https://www.ithome.com/",
      "category": "Blog"
    },
    {
      "title": "华为 Mate 80 Pro Max 手机官宣搭载全金属玄武架构",
      "link": "https://www.ithome.com/0/899/688.htm",
      "date": "2025-11-24 11:08",
      "author": "IT之家",
      "timestamp": 1763953727.0,
      "summary": "IT之家 11 月 24 日消息，今天上午，华为终端发文宣布，Mate 80 Pro Max 搭载全金属玄武架构。从官方放出的宣传视频来看，该机将支持防摔、防水、防磕碰等特性，在演示视频内的一系列“暴力测试”中，官方宣称“本片没有一台 Mate 手机受到伤害”。 官方先前放出的预告也显示，全新 Ma",
      "source_url": "https://www.ithome.com/",
      "category": "Blog"
    },
    {
      "title": "超级大翻车？微软承认从2025年7月更新开始Windows 11核心功能几乎都存在问题",
      "link": "https://www.landiannews.com/archives/111203.html",
      "date": "2025-11-24 11:08",
      "author": "蓝点网",
      "timestamp": 1763953690.0,
      "summary": "#系统资讯 超级无敌大翻车！微软承认从 2025 年 7 月更新开始 Windows 11 核心功能几乎都存在问题，问题根源是 XAML 组件和程序包更新。具体来说用户可能会碰到资源管理器进程崩溃、shellhost 崩溃、开始菜单问题、设置问题、出失败 XAML 视图时应用程序崩溃、资源管理器启动",
      "source_url": "https://www.landiannews.com",
      "category": "Blog"
    },
    {
      "title": "美的将推“表情包”空调：内置 60+ 种表情，支持远程 DIY",
      "link": "https://www.ithome.com/0/899/687.htm",
      "date": "2025-11-24 11:06",
      "author": "IT之家",
      "timestamp": 1763953562.0,
      "summary": "IT之家 11 月 24 日消息，美的集团今日发布消息，将于 11 月 29 日推出一款“无风感空调・可爱多”新品。这款空调搭载了“萌趣智绘屏”，内置 60+ 种表情，支持远程 DIY 定制创意。从海报可以看到，这款空调采用立式设计，空调面板上配有点阵屏幕，可以显示类似眼睛的图案。IT之家查询发现，",
      "source_url": "https://www.ithome.com/",
      "category": "Blog"
    },
    {
      "title": "晶采观察丨全运会小潮玩激活大市场 赛事流量“变现”经济增量",
      "link": "https://www.chinanews.com.cn/sh/2025/11-24/10520616.shtml",
      "date": "2025-11-24 11:05",
      "author": "中新网社会新闻",
      "timestamp": 1763953528.0,
      "summary": "11月21日，第十五届全国运动会闭幕式在广东深圳前海欢乐剧场举行。回顾本届全运会，“体育+”发挥了巨大的乘数效应，其中，有一对“顶流”很受关注，以中华白海豚为原型的吉祥物“喜洋洋”“乐融融”，凭借活泼可爱的形象和表演“出圈”，相关文创周边掀起抢购热潮，至今热度仍在持续攀升。截至11月15日，十五运会",
      "source_url": "http://www.chinanews.com/society.shtml",
      "category": "News"
    },
    {
      "title": "高铁从我家乡穿过",
      "link": "https://www.chinanews.com.cn/sh/2025/11-24/10520612.shtml",
      "date": "2025-11-24 10:57",
      "author": "中新网社会新闻",
      "timestamp": 1763953041.0,
      "summary": "人民日报",
      "source_url": "http://www.chinanews.com/society.shtml",
      "category": "News"
    },
    {
      "title": "Windows 11新版记事本已经可以通过MD格式添加表格 是的记事本现在都支持表格了",
      "link": "https://www.landiannews.com/archives/111202.html",
      "date": "2025-11-24 10:53",
      "author": "蓝点网",
      "timestamp": 1763952789.0,
      "summary": "#软件资讯 夭寿啦！Windows 11 内置的笔记本应用现在甚至支持表格，体验与 Word 中插入表格类似，不过这是通过 MarkDown 格式实现的。微软推出的新版记事本应用扩展 MD 格式支持，此次新增插入表格，用户可以从菜单插入 MD 表格，并通过右键增加或删除表格等。查看全文：https:",
      "source_url": "https://www.landiannews.com",
      "category": "Blog"
    },
    {
      "title": "面条厂里“搓飞机”！起底“三无”飞机黑色产业链",
      "link": "https://www.chinanews.com.cn/sh/2025/11-24/10520610.shtml",
      "date": "2025-11-24 10:52",
      "author": "中新网社会新闻",
      "timestamp": 1763952763.0,
      "summary": "2025年国务院政府工作报告明确指出，“开展新技术新产品新场景大规模应用示范行动，推动商业航天、低空经济等新兴产业安全健康发展”，报告中着重提到的“安全”二字，重如泰山。",
      "source_url": "http://www.chinanews.com/society.shtml",
      "category": "News"
    },
    {
      "title": "惩治税收犯罪！一人骗取出口退税8.7亿余元被判无期",
      "link": "https://www.chinanews.com.cn/sh/2025/11-24/10520608.shtml",
      "date": "2025-11-24 10:49",
      "author": "中新网社会新闻",
      "timestamp": 1763952585.0,
      "summary": "我国税收监管正从“以票管税”向“以数治税”分类精准监管转变，对税收违法犯罪行为的查处力度不断加大。同时，危害税收征管犯罪也出现了新变化，犯罪手法不断翻新，作案手段更加隐蔽，如利用“阴阳合同”逃税、秘密转移财产逃避追缴欠税等；职业化专业化特征明显，信息化水平提升，智能化越来越高，导致不少案件发现难、查",
      "source_url": "http://www.chinanews.com/society.shtml",
      "category": "News"
    },
    {
      "title": "依法惩治危害税收征管犯罪，最高法发布典型案例",
      "link": "https://www.chinanews.com.cn/sh/2025/11-24/10520601.shtml",
      "date": "2025-11-24 10:43",
      "author": "中新网社会新闻",
      "timestamp": 1763952210.0,
      "summary": "中新网北京11月24日电(记者 高萌)财政是国家治理的基础和重要支柱，税收是财政收入的最主要来源，也是国家实现宏观调控的重要手段。危害税收征管犯罪侵害国家税收利益，影响国家财政稳定，破坏经济发展秩序，损害社会公平正义，危害极大。",
      "source_url": "http://www.chinanews.com/society.shtml",
      "category": "News"
    },
    {
      "title": "微软宣布Windows Server 2025是支持WINS名称解析服务的最终版本 后续将弃用",
      "link": "https://www.landiannews.com/archives/111191.html",
      "date": "2025-11-24 10:37",
      "author": "蓝点网",
      "timestamp": 1763951861.0,
      "summary": "#系统资讯 微软宣布 Windows Server 2025 是支持 WINS 名称解析服务的最终版本，后续 Windows Server 将彻底删除该组件，微软建议企业尽早迁移到具有现代化支持的 DNS 系统。WINS 最初于 1994 年发布，现在仍然使用该服务的企业已经比较少了，微软提前 10",
      "source_url": "https://www.landiannews.com",
      "category": "Blog"
    },
    {
      "title": "大风沙尘雨雪“组团来袭” 宁夏局地阵风达12级",
      "link": "https://www.chinanews.com.cn/sh/2025/11-24/10520593.shtml",
      "date": "2025-11-24 10:23",
      "author": "中新网社会新闻",
      "timestamp": 1763951009.0,
      "summary": "中新网银川11月24日电 (记者 杨迪)刚经历完一轮“快闪型”冷空气，宁夏近日又遭遇大风、沙尘、雨雪天气“组团来袭”。23日夜间至24日凌晨，宁夏出现大风天气，阵风普遍在8级～10级，局地出现12级阵风。",
      "source_url": "http://www.chinanews.com/society.shtml",
      "category": "News"
    },
    {
      "title": "微软正在通过后台预加载模式提升Windows 11资源管理器性能 降低卡顿带来的负面影响",
      "link": "https://www.landiannews.com/archives/111190.html",
      "date": "2025-11-24 10:23",
      "author": "蓝点网",
      "timestamp": 1763950992.0,
      "summary": "#系统资讯 微软正在测试通过将资源管理器预加载到内存中来提升 Windows 11 资源管理器性能，降低因为卡顿 0.3~1 秒导致整体加载时间太长。资源管理器问题并非启动慢，而是启动后加载文件夹内容慢，部分用户经常看到白屏或显示正在处理，微软的解决方案是比较迂回的，并非直接解决加载问题，而是提高资",
      "source_url": "https://www.landiannews.com",
      "category": "Blog"
    },
    {
      "title": "Valve透露蒸汽机(Steam Machine)不会亏本出售硬件再靠卖游戏赚钱 而是正常价销售",
      "link": "https://www.landiannews.com/archives/111189.html",
      "date": "2025-11-24 10:04",
      "author": "蓝点网",
      "timestamp": 1763949889.0,
      "summary": "#硬件设备 Valve 高管透露蒸汽机 Steam Machine 不会通过降价销售硬件再卖游戏的方式赚钱，也就是硬件就按照硬件价格会，不会为了抢占市场降价补贴用户。Valve 高管称其最终价格应该与用户使用相同零件组装的 PC 类似，但蒸汽机提供更好的体验，这是玩家自己组装无法获得的游戏体验。查看",
      "source_url": "https://www.landiannews.com",
      "category": "Blog"
    },
    {
      "title": "谁能申领一次性创业补贴？人社部解答",
      "link": "https://www.chinanews.com.cn/sh/2025/11-24/10520535.shtml",
      "date": "2025-11-24 09:53",
      "author": "中新网社会新闻",
      "timestamp": 1763949189.0,
      "summary": "中新网11月24日电 谁能申领一次性创业补贴？人社部11月24日通过官方微信公众号作出解答。",
      "source_url": "http://www.chinanews.com/society.shtml",
      "category": "News"
    },
    {
      "title": "谷歌发文驳斥所谓Gmail会默认使用用户邮件训练AI模型 也不存在所谓的开关",
      "link": "https://www.landiannews.com/archives/111188.html",
      "date": "2025-11-24 09:49",
      "author": "蓝点网",
      "timestamp": 1763948963.0,
      "summary": "#软件资讯 谷歌发文驳斥所谓的 Gmail 会默认使用用户邮件训练 AI 模型的说法，称没有更改任何人的设置，也不存在所谓的开关。至于流传的智能功能则是 Gmail 已经上线多年的功能，该功能可以禁用，但是否禁用都与 Gemini 训练数据无关。查看全文：https://ourl.co/111188",
      "source_url": "https://www.landiannews.com",
      "category": "Blog"
    },
    {
      "title": "冷空气接二连三影响我国 北方多地气温将现快节奏波动",
      "link": "https://www.chinanews.com.cn/sh/2025/11-24/10520541.shtml",
      "date": "2025-11-24 09:13",
      "author": "中新网社会新闻",
      "timestamp": 1763946839.0,
      "summary": "中国天气网讯 进入11月下旬，影响我国的冷空气较为频繁。目前，一股较强冷空气正自西向东影响我国，今明天(11月24日至25日)，冷空气继续东移南下，东北、华北东部到华南等地都将出现降温。紧接着，25日至27日，又将有新一股冷空气影响我国。此外，我国西南地区、东北等地雨雪天气频繁，局地或现大雪。",
      "source_url": "http://www.chinanews.com/society.shtml",
      "category": "News"
    },
    {
      "title": "8位具身智能顶流聊起“非共识”：数据、世界模型、花钱之道",
      "link": "https://36kr.com/p/3566363100674944?f=rss",
      "date": "2025-11-24 08:54",
      "author": "36氪",
      "timestamp": 1763945681.0,
      "summary": "文｜富充\n  编辑｜苏建勋\n  “如果给你的企业100亿元来推进具身智能的发展，这笔钱你会怎么花？”\n  在11月20日举行的2025智源具身Open Day圆桌论坛上，主持人抛出了这样一个开放性问题。\n  面对这个问题的嘉宾，来自8家国内具身行业的顶流企业机构：\n  智源研究院院长王仲远\n  智元",
      "source_url": "http://36kr.com",
      "category": "Blog"
    },
    {
      "title": "山东邹平：针对“三无飞机”成立调查组 全市排查",
      "link": "https://www.chinanews.com.cn/sh/2025/11-24/10520523.shtml",
      "date": "2025-11-24 08:23",
      "author": "中新网社会新闻",
      "timestamp": 1763943828.0,
      "summary": "总台报道有反馈丨山东邹平：针对“三无飞机”成立调查组 全市排查",
      "source_url": "http://www.chinanews.com/society.shtml",
      "category": "News"
    },
    {
      "title": "中央气象台：较强冷空气继续影响我国",
      "link": "https://www.chinanews.com.cn/sh/2025/11-24/10520519.shtml",
      "date": "2025-11-24 08:05",
      "author": "中新网社会新闻",
      "timestamp": 1763942755.0,
      "summary": "中新网11月24日电 据中央气象台网站24日消息，昨日，甘肃内蒙古四川等地出现降雪，新疆甘肃青海内蒙古等地出现大风降温沙尘。预计24日至25日，较强冷空气影响我国中东部地区，西北地区东部、内蒙古中西部、华北、黄淮及东部海域有大风，华北西部等地有沙尘天气；关注大风、降温、沙尘、积雪结冰等对设施安全、能",
      "source_url": "http://www.chinanews.com/society.shtml",
      "category": "News"
    },
    {
      "title": "8点1氪｜霸王茶姬创始人发朋友圈辟谣；俞敏洪再发全员信道歉，回应被叫“老登”；《哪吒之魔童闹海》未入围奥斯卡大名单",
      "link": "https://36kr.com/p/3566311519796104?f=rss",
      "date": "2025-11-24 08:02",
      "author": "36氪",
      "timestamp": 1763942553.0,
      "summary": "今日热点导览\n  \n   西贝降价，幅度在5%—20%不等\n   移动金融APP加速瘦身\n   胖东来投资1亿成立新公司\n   比亚迪宁德时代2名科学家入选院士\n   网传小米汽车工厂内电池产线起火，小米官方澄清\n  \n  TOP3大新闻\n  霸王茶姬创始人发朋友圈辟谣\n  日前霸王茶姬创始人张俊杰",
      "source_url": "http://36kr.com",
      "category": "Blog"
    },
    {
      "title": "围剿“流感神药”奥司他韦，药厂卷起“一次治疗”新战场",
      "link": "https://36kr.com/p/3562392632458371?f=rss",
      "date": "2025-11-24 08:00",
      "author": "36氪",
      "timestamp": 1763942400.0,
      "summary": "“中招了。”\n  11月中旬的一个早上，上海白领阿良醒来就觉得自己嗓子发紧、浑身无力。还不到中午，她开始隐隐感受到发烧的迹象，和前些天刚好的风寒感冒“完全不是一个感觉”。阿良随即意识到，自己大概率是感染了流感。\n  2025年冬天，流感季整体提前了将近1个月。国家疾控局在11月10日的新闻发布会上表",
      "source_url": "http://36kr.com",
      "category": "Blog"
    },
    {
      "title": "哈拉湖边的垃圾，谁来清理？",
      "link": "https://www.chinanews.com.cn/sh/2025/11-24/10520515.shtml",
      "date": "2025-11-24 07:52",
      "author": "中新网社会新闻",
      "timestamp": 1763941923.0,
      "summary": "青海哈拉湖生态脆弱，车辆碾压可能破坏植被，需数十年恢复",
      "source_url": "http://www.chinanews.com/society.shtml",
      "category": "News"
    },
    {
      "title": "上下班途中、居家工作，哪些情形可认定工伤",
      "link": "https://www.chinanews.com.cn/sh/2025/11-24/10520514.shtml",
      "date": "2025-11-24 07:49",
      "author": "中新网社会新闻",
      "timestamp": 1763941779.0,
      "summary": "上下班途中、居家工作，哪些情形可认定工伤(民生一线)",
      "source_url": "http://www.chinanews.com/society.shtml",
      "category": "News"
    },
    {
      "title": "200余个地级及以上城市开展城市管理进社区工作",
      "link": "https://www.chinanews.com.cn/sh/2025/11-24/10520513.shtml",
      "date": "2025-11-24 07:47",
      "author": "中新网社会新闻",
      "timestamp": 1763941679.0,
      "summary": "本报北京11月23日电  (记者丁怡婷)在日前举行的全国城市更新工作推进会上，住房城乡建设部表示，要下功夫抓好系统治理和基层治理，推动城市管理进社区等工作，推进城市治理现代化。",
      "source_url": "http://www.chinanews.com/society.shtml",
      "category": "News"
    },
    {
      "title": "北京今天气温下降并伴8级左右阵风 山区有雨夹雪或雪",
      "link": "https://www.chinanews.com.cn/sh/2025/11-24/10520512.shtml",
      "date": "2025-11-24 07:45",
      "author": "中新网社会新闻",
      "timestamp": 1763941547.0,
      "summary": "中国天气网讯 今天(11月24日)，北京天气阴转晴，山区有雨夹雪或雪，受冷空气影响气温下降，并伴有8级左右阵风，公众请注意防风保暖。明后天，北京气温持续较低，最高气温7至8°C，最低气温在冰点以下，仍需注意保暖。",
      "source_url": "http://www.chinanews.com/society.shtml",
      "category": "News"
    },
    {
      "title": "多地开展科学保护，我国大熊猫种群数量稳定发展",
      "link": "https://www.chinanews.com.cn/sh/2025/11-24/10520511.shtml",
      "date": "2025-11-24 07:43",
      "author": "中新网社会新闻",
      "timestamp": 1763941429.0,
      "summary": "多地开展科学保护，我国大熊猫种群数量稳定发展",
      "source_url": "http://www.chinanews.com/society.shtml",
      "category": "News"
    },
    {
      "title": "距章程到期仅剩8个月 美国政府效率部已“不复存在”",
      "link": "https://www.cnbeta.com.tw/articles/tech/1537642.htm",
      "date": "2025-11-24 07:17",
      "author": "cnBeta.COM.TW RSS订阅",
      "timestamp": 1763939876.0,
      "summary": "美国总统唐纳德・特朗普旗下的 “政府效率部门”（DOGE）在任期还剩 8 个月时宣布解散。该部门当初高调成立，是特朗普承诺缩减政府规模的象征，但批评人士称其几乎没有实现可量化的开支节约。 阅读全文",
      "source_url": "https://www.cnbeta.com.tw",
      "category": "Blog"
    },
    {
      "title": "奇瑞复刻路虎攀爬天门山溜车撞断护栏 官方公告称已修复完毕",
      "link": "https://www.cnbeta.com.tw/articles/tech/1537640.htm",
      "date": "2025-11-24 07:15",
      "author": "cnBeta.COM.TW RSS订阅",
      "timestamp": 1763939738.0,
      "summary": "奇瑞复刻路虎攀爬天门山溜车撞断的护栏目前已经修复完毕。天门山“天梯”是游客通往天门洞的主要通道，全长近300米，垂直落差达150米，共有999级台阶，以坡度陡峭著称。 阅读全文",
      "source_url": "https://www.cnbeta.com.tw",
      "category": "Blog"
    },
    {
      "title": "黄仁勋：NVIDIA已不再是游戏显卡公司",
      "link": "https://www.cnbeta.com.tw/articles/tech/1537638.htm",
      "date": "2025-11-24 00:19",
      "author": "cnBeta.COM.TW RSS订阅",
      "timestamp": 1763914767.0,
      "summary": "NVIDIA近日公布的财报显示，其在2025财年第三季度实现了高达570亿美元的营收。这一惊人的成绩主要得益于英伟达在AI热潮中所扮演的关键角色，而且似乎该公司的公开形象正在随之转变。 阅读全文",
      "source_url": "https://www.cnbeta.com.tw",
      "category": "Blog"
    },
    {
      "title": "Intel 18A处理器CPU、GPU及工艺三重升级：赌赢了一举翻身",
      "link": "https://www.cnbeta.com.tw/articles/tech/1537636.htm",
      "date": "2025-11-23 23:40",
      "author": "cnBeta.COM.TW RSS订阅",
      "timestamp": 1763912450.0,
      "summary": "Intel已经确定要在明年1月份的CES展会上正式发布Panther Lake处理器，这是18A工艺的首款消费级产品，正式名称会是酷睿Ultra 300系列。酷睿Ultra 300日前有ES版样品性能偷跑出来，但分数离奇地低，显然还不太正常，目前还无法给出评价。 阅读全文",
      "source_url": "https://www.cnbeta.com.tw",
      "category": "Blog"
    },
    {
      "title": "iOS 27将重点优化性能与AI功能",
      "link": "https://www.cnbeta.com.tw/articles/tech/1537634.htm",
      "date": "2025-11-23 23:20",
      "author": "cnBeta.COM.TW RSS订阅",
      "timestamp": 1763911251.0,
      "summary": "彭博社消息称，苹果即将于2026年发布的 iOS 27 操作系统，其重点将放在提升性能和人工智能（AI）能力，而不是添加大量新功能。近年来，“Liquid Glass”界面的引入被认为是苹果操作系统的重大革新，用户习惯每次系统升级都有新功能。不过，iOS 27的策略将有所不同，苹果决定更多关注系统性",
      "source_url": "https://www.cnbeta.com.tw",
      "category": "Blog"
    },
    {
      "title": "科学家称大蒜提取物漱口水或可媲美主流杀菌剂",
      "link": "https://www.cnbeta.com.tw/articles/science/1537632.htm",
      "date": "2025-11-23 23:20",
      "author": "cnBeta.COM.TW RSS订阅",
      "timestamp": 1763911224.0,
      "summary": "沙迦大学最新研究综述显示，大蒜提取物在抑制口腔有害微生物方面，或可与长期被视为“金标准”的杀菌漱口水——氯己定（Chlorhexidine）媲美。虽然大蒜漱口水在使用时可能更易带来不适感，但其杀菌活性持续时间更长。该成果已发表在《草药医学期刊》（Journal of Herbal Medicine）",
      "source_url": "https://www.cnbeta.com.tw",
      "category": "Blog"
    },
    {
      "title": "苹果首席执行官Tim Cook不会在2026年退休",
      "link": "https://www.cnbeta.com.tw/articles/tech/1537630.htm",
      "date": "2025-11-23 23:17",
      "author": "cnBeta.COM.TW RSS订阅",
      "timestamp": 1763911044.0,
      "summary": "近日有报道称，苹果公司首席执行官Tim Cook或将在2026年WWDC之前宣布退休，并启动继任计划，但这一消息被证伪，库克并未计划在该时间点退休。此前，《金融时报》曾声称苹果将在2026年初公布由约翰·特努斯接任库克的方案，虽然库克及高管团队未来五年内都可能退休，但库克离开看起来还很遥远。 阅读全",
      "source_url": "https://www.cnbeta.com.tw",
      "category": "Blog"
    },
    {
      "title": "11年将CPU份额提升40倍 苏姿丰：AMD有望成为第一",
      "link": "https://www.cnbeta.com.tw/articles/tech/1537628.htm",
      "date": "2025-11-23 23:16",
      "author": "cnBeta.COM.TW RSS订阅",
      "timestamp": 1763910962.0,
      "summary": "半导体行业女性力量不可忽视，AMD CEO苏姿丰就是行业内的铁娘子，她担任CEO一职已有11年，带领AMD重新走向辉煌。日前在接受采访时，苏姿丰谈到了自己过往的经历，坦言AMD抓住机遇的关键就是在关键时刻做出正确决策，知道科技会往哪里走，就要在哪里投资，这就是AMD在做的。 阅读全文",
      "source_url": "https://www.cnbeta.com.tw",
      "category": "Blog"
    },
    {
      "title": "iPhone 17 Pro Max成功破解运行iPadOS 体验神似Mac",
      "link": "https://www.cnbeta.com.tw/articles/tech/1537626.htm",
      "date": "2025-11-23 23:15",
      "author": "cnBeta.COM.TW RSS订阅",
      "timestamp": 1763910932.0,
      "summary": "虽然iOS和iPadOS在底层平台相似，但苹果一直限制iPhone用户使用iPad独有的多任务和桌面级功能。不过近日一位iPhone 17 Pro Max用户通过一个漏洞成功破解了这款手机，并使其运行iPadOS，实现了神似Mac的桌面体验。 阅读全文",
      "source_url": "https://www.cnbeta.com.tw",
      "category": "Blog"
    },
    {
      "title": "深埋了34年的苹果Mac Classic II  Bug被发现",
      "link": "https://www.cnbeta.com.tw/articles/tech/1537624.htm",
      "date": "2025-11-23 23:11",
      "author": "cnBeta.COM.TW RSS订阅",
      "timestamp": 1763910710.0,
      "summary": "一名电脑爱好者最近挖掘出一个存在于苹果Mac Classic II ROM代码中长达34年的Bug。令人惊讶的是，这个原本足以导致系统启动崩溃的漏洞，却从未在真实的硬件上出现，背后则是摩托罗拉68030 CPU中一个未被记录的功能，悄无声息地抵消了这一缺陷。 阅读全文",
      "source_url": "https://www.cnbeta.com.tw",
      "category": "Blog"
    },
    {
      "title": "育碧大力称赞AI：影响堪比从2D转向3D游戏 每个团队都在使用AI",
      "link": "https://www.cnbeta.com.tw/articles/game/1537622.htm",
      "date": "2025-11-23 23:11",
      "author": "cnBeta.COM.TW RSS订阅",
      "timestamp": 1763910672.0,
      "summary": "育碧认为，生成式AI对游戏业的影响堪比从2D向3D的革命性转变，而这项技术正在全公司范围内被采纳。此前，EA公司CEO在回应在全公司推广AI引起的争议时暗示会继续推进对AI的使用。 阅读全文",
      "source_url": "https://www.cnbeta.com.tw",
      "category": "Blog"
    },
    {
      "title": "人们认为最安全的饮用水源 - 瓶装水并不像你想象的那样安全",
      "link": "https://www.cnbeta.com.tw/articles/science/1537620.htm",
      "date": "2025-11-23 20:14",
      "author": "cnBeta.COM.TW RSS订阅",
      "timestamp": 1763900073.0,
      "summary": "一项新研究指出，瓶装水并不像人们普遍认为的那样安全。该研究团队在危地马拉实地调查后发现，人们认为最安全的饮用水源实际上可能污染最严重，而一些不被信赖的水源反而更加干净。 阅读全文",
      "source_url": "https://www.cnbeta.com.tw",
      "category": "Blog"
    },
    {
      "title": "ASML在美首建技术学院 年培训千名芯片设备工程师",
      "link": "https://www.cnbeta.com.tw/articles/tech/1537618.htm",
      "date": "2025-11-23 20:12",
      "author": "cnBeta.COM.TW RSS订阅",
      "timestamp": 1763899943.0,
      "summary": "荷兰光刻设备制造商阿斯麦（ASML）于本周四在美国凤凰城正式启用其全新建设的技术培训学院，旨在为当地芯片产业培养能够维护和维修其高端光刻设备的专业工程师。该学院位于凤凰城机场附近，车程仅数分钟，规划年培训能力超过1000人，专注于为ASML复杂的光刻系统提供技术服务支持。 阅读全文",
      "source_url": "https://www.cnbeta.com.tw",
      "category": "Blog"
    },
    {
      "title": "三星追加19亿美元升级美工厂 提升CMOS图像传感器生产能力",
      "link": "https://www.cnbeta.com.tw/articles/tech/1537616.htm",
      "date": "2025-11-23 20:07",
      "author": "cnBeta.COM.TW RSS订阅",
      "timestamp": 1763899649.0,
      "summary": "三星电子计划向其位于美国得克萨斯州奥斯汀的半导体晶圆厂追加约19亿美元投资，用于升级现有产线并引进先进芯片制造设备，进一步强化其在美国本土的高端制造能力。 阅读全文",
      "source_url": "https://www.cnbeta.com.tw",
      "category": "Blog"
    },
    {
      "title": "长鑫DDR5内存新品发布 最高速率达8000Mbps",
      "link": "https://www.cnbeta.com.tw/articles/tech/1537614.htm",
      "date": "2025-11-23 20:04",
      "author": "cnBeta.COM.TW RSS订阅",
      "timestamp": 1763899485.0,
      "summary": "在今天开幕的IC China 2025（中国国际半导体博览会）上，长鑫存储正式发布了其最新一代DDR5产品系列。该系列产品在速率和容量维度均达到国际领先水平，最高速率高达8000Mbps，最高颗粒容量达到24Gb，并同步推出了覆盖全应用领域的七大模组产品。 阅读全文",
      "source_url": "https://www.cnbeta.com.tw",
      "category": "Blog"
    },
    {
      "title": "让大熊猫全球“圈粉”，成都为什么行？",
      "link": "https://www.infzm.com/contents/308265",
      "date": "2025-11-23 19:00",
      "author": "南方周末-新闻",
      "timestamp": 1763895600.0,
      "summary": "南方周末研究员 郭倩倩\n                    \n                    \n                                        责任编辑：戴春晨",
      "source_url": "https://www.infzm.com/contents?term_id=2",
      "category": "News"
    },
    {
      "title": "被窝推出家装资金存管一周年，超1.6万单、24亿资金“安全落地”",
      "link": "https://36kr.com/p/3565477319736454?f=rss",
      "date": "2025-11-23 18:01",
      "author": "36氪",
      "timestamp": 1763892091.0,
      "summary": "我国家装行业已步入万亿级市场规模，且呈现结构性增长态势。据艾瑞咨询《2024年中国家装行业白皮书》数据显示，2024年家装行业细分领域中，整装服务作为主流模式，市场规模已达5860亿元，占行业总规模的42.3%，成为占比最高的服务类型；施工服务紧随其后，占比约28.7%，市场规模约3980亿元；设计",
      "source_url": "http://36kr.com",
      "category": "Blog"
    },
    {
      "title": "米哈游次时代新作公布实机演示；腾讯战投育碧11.6亿欧元；Unity和Epic宣布合作 |  氪游周报",
      "link": "https://36kr.com/p/3565236976532360?f=rss",
      "date": "2025-11-23 13:49",
      "author": "36氪",
      "timestamp": 1763876958.0,
      "summary": "文 | 贝果树‍&nbsp;\n  编辑 | 刘士武\n  新游速递\n  米哈游新作《Varsapura》公布实机演示\n  11月21日，米哈游和HoYoverse联合研发的旗舰新作《Varsapura》（雨之城）公布首段长达31分钟的实机演示。这款作品由米哈游联合创始人蔡浩宇一手负责，采用虚幻引擎5开",
      "source_url": "http://36kr.com",
      "category": "Blog"
    },
    {
      "title": "赵英民：绿色转型不是负担，越早行动越早受益",
      "link": "https://www.infzm.com/contents/308241",
      "date": "2025-11-23 13:00",
      "author": "南方周末-新闻",
      "timestamp": 1763874000.0,
      "summary": "有的国家连电力都不稳定，那我们就帮助他们跳过化石能源阶段，从一开始就用上太阳能、风能等可再生的清洁能源电力。\n\n不同的发展中国家能力有差异，这是事实，但每个国家都要根据自身的能力，推动气候治理往前走。我们强调的是尊重各国发展阶段，让大家在能力范围内尽最大努力。",
      "source_url": "https://www.infzm.com/contents?term_id=2",
      "category": "News"
    },
    {
      "title": "冒用同名者成果、证书有PS痕迹？“首席科学家”郭伟的魔幻履历",
      "link": "https://www.infzm.com/contents/308253",
      "date": "2025-11-23 12:08",
      "author": "南方周末-新闻",
      "timestamp": 1763870917.0,
      "summary": "“我们以为经过学校审核的人不会有问题。”王超的创业项目需要有头衔的专家坐镇，郭伟爽快应邀，发来37页PPT。\n\n“叫郭伟的人多了。”郭伟在博导招生资格申请中称，发表过6篇国际期刊论文。南方周末记者查询发现，论文作者确有“Guo Wei”，但来自不同科研机构。\n\n一位共同申请专利的研究人员发现，郭伟的",
      "source_url": "https://www.infzm.com/contents?term_id=2",
      "category": "News"
    }
  ]
}