{
  "update_time": "2025-10-24",
  "articles": [
    {
      "title": "黄金和债券基金今年吸金规模势创纪录，资金亦强势流入股票和现金基金",
      "link": "https://36kr.com/newsflashes/3523159864859524?f=rss",
      "date": "2025-10-24 20:23",
      "author": "36氪",
      "timestamp": 1761308612.0,
      "summary": "随着不同类别资产之间传统的相关性被打破，股票、现金、黄金和债券基金的年度资金流入规模有望位居历史前列。据美银基于EPFR Global数据计算，从年迄今数据的年化表现来看，2025年股票基金有望吸引6930亿美元的资金流入。该行策略师在报告中指出，这将创历史第三高纪录。现金基金预计将吸引1.1万亿美",
      "source_url": "http://36kr.com",
      "category": "Blog"
    },
    {
      "title": "神工股份：三季度净利润2233.16万元，同比下降1.73%",
      "link": "https://36kr.com/newsflashes/3523158519487366?f=rss",
      "date": "2025-10-24 20:22",
      "author": "36氪",
      "timestamp": 1761308530.0,
      "summary": "36氪获悉，神工股份发布2025年三季报，公司第三季度营业收入1.07亿元，同比增长20.91%；归属于上市公司股东的净利润2233.16万元，同比下降1.73%。",
      "source_url": "http://36kr.com",
      "category": "Blog"
    },
    {
      "title": "阿布扎比投资局将透过管理账户向对冲基金投入400亿美元进行对冲",
      "link": "https://36kr.com/newsflashes/3523155097836679?f=rss",
      "date": "2025-10-24 20:18",
      "author": "36氪",
      "timestamp": 1761308321.0,
      "summary": "阿布扎比投资局（ADIA）表示将透过管理账户向对冲基金投入400亿美元进行对冲。（财联社）",
      "source_url": "http://36kr.com",
      "category": "Blog"
    },
    {
      "title": "国产手机首次：OPPO 将实现“支付宝碰一下”发红包",
      "link": "https://www.ithome.com/0/892/203.htm",
      "date": "2025-10-24 20:15",
      "author": "IT之家",
      "timestamp": 1761308135.0,
      "summary": "IT之家 10 月 24 日消息，据蚂蚁集团今日消息，OPPO 与蚂蚁集团正式签署战略合作协议。双方将围绕 AI 智能体、服务生态、“碰一下”、医疗健康服务、保险、用户体验等领域展开深入合作，携手打造以用户为中心的智慧生活体验。IT之家从合作公告获悉，双方将重点聚焦 AI 智能体方面的合作，基于对用",
      "source_url": "https://www.ithome.com/",
      "category": "Blog"
    },
    {
      "title": "《英雄联盟》S15 瑞士轮明日迎来最终轮次：TES BLG 内战，其一保送八强",
      "link": "https://www.ithome.com/0/892/202.htm",
      "date": "2025-10-24 20:14",
      "author": "IT之家",
      "timestamp": 1761308044.0,
      "summary": "IT之家 10 月 24 日消息，在今日的 2025 全球总决赛瑞士轮第八日比赛中，BLG 与 T1 均 2:0 战胜对手，打入瑞士轮最后一轮的 2-2 对阵（BO3）。根据抽签结果，来自 LPL 的一号种子 BLG 明日将与三号种子 TES 开启内战，胜者将进入八强淘汰赛阶段。IT之家附抽签结果如",
      "source_url": "https://www.ithome.com/",
      "category": "Blog"
    },
    {
      "title": "聚焦“山水·乡韵·新生” 《东安印象》摄影展解锁湖南县域发展新图景",
      "link": "http://www.chinanews.com/sh/2025/10-24/10503993.shtml",
      "date": "2025-10-24 20:13",
      "author": "中新网社会新闻",
      "timestamp": 1761307997.0,
      "summary": "中新网长沙10月24日电 (唐小晴 陈荣景 严洁)24日，《东安印象》摄影大展在位于长沙的谢子龙影像艺术馆开幕。展览以镜头捕捉山水灵韵、用画面传递乡土温度，旨在展现湖南东安县生态之形、人文之魂、发展之梦，让民众感受东安在乡村振兴、文旅融合发展中的独特魅力与蓬勃活力。",
      "source_url": "http://www.chinanews.com/society.shtml",
      "category": "News"
    },
    {
      "title": "卫星化学：三季度净利润10.11亿元，同比下降38.21%",
      "link": "https://36kr.com/newsflashes/3523146064747649?f=rss",
      "date": "2025-10-24 20:09",
      "author": "36氪",
      "timestamp": 1761307770.0,
      "summary": "36氪获悉，卫星化学发布2025年三季报，公司第三季度营业收入113.11亿元，同比下降12.15%；归属于上市公司股东的净利润10.11亿元，同比下降38.21%。",
      "source_url": "http://36kr.com",
      "category": "Blog"
    },
    {
      "title": "国家外汇管理局：加强外汇市场“宏观审慎+微观监管”两位一体管理，完善跨境资金流动监测预警体系",
      "link": "https://36kr.com/newsflashes/3523143083350914?f=rss",
      "date": "2025-10-24 20:06",
      "author": "36氪",
      "timestamp": 1761307588.0,
      "summary": "36氪获悉，10月24日，国家外汇管理局党组书记、局长朱鹤新主持召开党组会议。会议强调，维护外汇市场稳定和国家经济金融安全。加强外汇市场“宏观审慎+微观监管”两位一体管理，完善跨境资金流动监测预警体系，保持人民币汇率在合理均衡水平上的基本稳定，强化外汇领域监管全覆盖，严厉打击外汇领域违法违规活动。完",
      "source_url": "http://36kr.com",
      "category": "Blog"
    },
    {
      "title": "备战 iPhone 18 系列，苹果被曝已向三星下单 1300 万颗 10nm LPDDR5X 内存芯片",
      "link": "https://www.ithome.com/0/892/201.htm",
      "date": "2025-10-24 20:05",
      "author": "IT之家",
      "timestamp": 1761307508.0,
      "summary": "IT之家 10 月 24 日消息，据 The Bell 昨日报道，苹果正为 2026 年发布的 iPhone 18 系列提前布局供应链，三星电子已经收到了苹果对于 DRAM 扩大供应量的请求。据称，苹果已向三星电子预购约 1300 万颗 10nm LPDDR5X DRAM 内存芯片，这批芯片计划于明",
      "source_url": "https://www.ithome.com/",
      "category": "Blog"
    },
    {
      "title": "京东物流：未来 5 年采购 300 万台机器人、100 万台无人车和 10 万架无人机",
      "link": "https://www.ithome.com/0/892/200.htm",
      "date": "2025-10-24 20:04",
      "author": "IT之家",
      "timestamp": 1761307468.0,
      "summary": "IT之家 10 月 24 日消息，京东物流今日宣布，未来 5 年要采购 300 万台机器人、100 万台无人车和 10 万架无人机，全面投入物流供应链全链路场景。京东物流表示，今年京东 11.11，京东物流仅“狼族”系列机器人在全国超 20 个省份、全球超 10 个国家的规模化部署应用，覆盖仓储、分",
      "source_url": "https://www.ithome.com/",
      "category": "Blog"
    },
    {
      "title": "第十五届全国高校交通类学院党委书记论坛在长沙举行",
      "link": "http://www.chinanews.com/sh/2025/10-24/10503989.shtml",
      "date": "2025-10-24 20:03",
      "author": "中新网社会新闻",
      "timestamp": 1761307408.0,
      "summary": "中新网长沙10月24日电 (记者 徐志雄)10月24日，以“使命·融合·创新”为主题的第十五届全国高校交通类学院党委书记论坛，在长沙理工大学举行。来自中国26所高校交通类学院的党委书记、专家学者等60余位嘉宾齐聚一堂，共同探讨党建引领交通运输学科高质量发展。",
      "source_url": "http://www.chinanews.com/society.shtml",
      "category": "News"
    },
    {
      "title": "北京开辟城市水治理新路径 一体推进蓝绿空间建设",
      "link": "http://www.chinanews.com/sh/2025/10-24/10503995.shtml",
      "date": "2025-10-24 20:01",
      "author": "中新网社会新闻",
      "timestamp": 1761307278.0,
      "summary": "中新网北京10月24日电 以“生态城市融合共生”为主题的第二届生态治理(南森)大会24日在北京召开。大会上，由政府部门、央国企、科研机构共同发布“水系生态治理行动”，重点聚焦永定河、凉水河等流域治理，推动“碧水穿城映新景湿地润城筑未来”的目标落地，未来将通过技术共享、项目共建，破解城市水系治理难题，",
      "source_url": "http://www.chinanews.com/society.shtml",
      "category": "News"
    },
    {
      "title": "杨凌两大农业综合性平台启用 将助力“旱区农业新质生产力”建设",
      "link": "http://www.chinanews.com/sh/2025/10-24/10504003.shtml",
      "date": "2025-10-24 20:00",
      "author": "中新网社会新闻",
      "timestamp": 1761307240.0,
      "summary": "中新网陕西杨凌10月24日电 (梅镱泷 米蓓)杨凌种业展示交易中心、杨凌智慧农业装备展示交易中心暨杨凌自贸区设施农业装备及生产资料展示交易中心23日在陕西杨凌正式启用。",
      "source_url": "http://www.chinanews.com/society.shtml",
      "category": "News"
    },
    {
      "title": "QQ 鸿蒙版 App 邀测 9.1.90 版本升级，已支持视频拍摄、空间消息通知等",
      "link": "https://www.ithome.com/0/892/199.htm",
      "date": "2025-10-24 19:57",
      "author": "IT之家",
      "timestamp": 1761307077.0,
      "summary": "IT之家 10 月 24 日消息，QQ 鸿蒙版 App 今晚邀测 9.1.90 版本升级，具体活动时间为 10 月 24 日到 11 月 23 日。IT之家附测试说明如下：新增支持视频拍摄选图片支持切换系统相册目录新增空间消息通知网页图片长按支持保存和转发新增家校群班级打卡应用群相册评论支持发送表情",
      "source_url": "https://www.ithome.com/",
      "category": "Blog"
    },
    {
      "title": "2025年全国第七届“长江江豚保护日”活动在南京举行",
      "link": "http://www.chinanews.com/sh/2025/10-24/10504006.shtml",
      "date": "2025-10-24 19:54",
      "author": "中新网社会新闻",
      "timestamp": 1761306895.0,
      "summary": "中新网南京10月24日电 (记者 朱晓颖)24日，由中国渔业协会、中国科学院水生生物研究所、中国水产科学研究院淡水渔业研究中心联合主办的2025年长江江豚保护宣传活动暨第十六届国际淡水豚日宣传活动在南京举行。全国的50余家相关机构及百余位江豚保护研究领域的专家学者、机构和民间组织代表、志愿者参会。与",
      "source_url": "http://www.chinanews.com/society.shtml",
      "category": "News"
    },
    {
      "title": "消息称长安计划未来新车都基于 SDA 平台开发，已规划 7 款车型",
      "link": "https://www.ithome.com/0/892/197.htm",
      "date": "2025-10-24 19:52",
      "author": "IT之家",
      "timestamp": 1761306741.0,
      "summary": "IT之家 10 月 24 日消息，据雷峰网《新智驾》今日爆料，长安汽车已确定未来新车型将全面转向 SDA 平台开发，覆盖启源、深蓝、阿维塔等核心品牌。目前，SDA 平台已率先应用于启源 E07、Q07 和 A06 三款车型，即将上市的深蓝 L06 同样基于该平台开发。阿维塔品牌也计划于明年推出首款",
      "source_url": "https://www.ithome.com/",
      "category": "Blog"
    },
    {
      "title": "生态城市融合共生 第二届生态治理（南森）大会召开",
      "link": "http://www.chinanews.com/sh/2025/10-24/10503996.shtml",
      "date": "2025-10-24 19:51",
      "author": "中新网社会新闻",
      "timestamp": 1761306705.0,
      "summary": "中新网北京10月24日电  以“生态城市融合共生”为主题的第二届生态治理(南森)大会24日在北京召开。来自生态、园林、水务、融媒体等多个行业的50余家企业出席大会，中建生态、中国水务等多家知名进行企业主旨分享推介，达成发展共识，碰撞创新思路。",
      "source_url": "http://www.chinanews.com/society.shtml",
      "category": "News"
    },
    {
      "title": "上海专项整治网约车：加大对非法营运、违规派单等整治力度，从严监管平台",
      "link": "https://www.ithome.com/0/892/196.htm",
      "date": "2025-10-24 19:50",
      "author": "IT之家",
      "timestamp": 1761306621.0,
      "summary": "IT之家 10 月 24 日消息，据“第 4 焦点上海交警微发布”公众号，近日，为维护公平有序的网约车市场秩序，依法查处网约车非法客运及易致祸道路交通违法行为，提高网约车服务质量，保障乘客合法权益，上海市交通委执法总队、市公安局交管总队联合组织开展全市网约车联合治理专项整治行动。IT之家从文章获悉，",
      "source_url": "https://www.ithome.com/",
      "category": "Blog"
    },
    {
      "title": "金瓯无缺 “台湾义勇队档案文献展”开幕",
      "link": "http://www.chinanews.com/sh/2025/10-24/10503994.shtml",
      "date": "2025-10-24 19:49",
      "author": "中新网社会新闻",
      "timestamp": 1761306595.0,
      "summary": "10月23日，由北京市台联和福建省档案馆联合举办，全国台湾研究会、北京台资企业协会支持的“义勇挥戈 同心复疆——台湾义勇队档案文献展”在北京台湾会馆开幕。",
      "source_url": "http://www.chinanews.com/society.shtml",
      "category": "News"
    },
    {
      "title": "（乡村行·看振兴）黄河入晋第一村老牛湾：“农文旅”赋能，让村民吃上“旅游饭”",
      "link": "http://www.chinanews.com/sh/2025/10-24/10503990.shtml",
      "date": "2025-10-24 19:49",
      "author": "中新网社会新闻",
      "timestamp": 1761306551.0,
      "summary": "中新网忻州10月24日电 题：黄河入晋第一村老牛湾：“农文旅”赋能，让村民吃上“旅游饭”",
      "source_url": "http://www.chinanews.com/society.shtml",
      "category": "News"
    },
    {
      "title": "特朗普让科技巨头和加密货币为白宫宴会厅提供资金支持",
      "link": "https://www.cnbeta.com.tw/articles/tech/1532680.htm",
      "date": "2025-10-24 19:48",
      "author": "cnBeta.COM.TW RSS订阅",
      "timestamp": 1761306493.0,
      "summary": "美国总统特朗普正在拆除白宫东翼，以建造一座华丽的舞厅。总统表示，这笔耗资高达3亿美元的工程将不会由纳税人承担，费用将由私人捐赠者，包括其本人在内支付。 阅读全文",
      "source_url": "https://www.cnbeta.com.tw",
      "category": "Blog"
    },
    {
      "title": "候鸟迁飞通道国际科教联盟入选UNESCO“科学十年”",
      "link": "http://www.chinanews.com/sh/2025/10-24/10503991.shtml",
      "date": "2025-10-24 19:47",
      "author": "中新网社会新闻",
      "timestamp": 1761306475.0,
      "summary": "中新网北京10月24日电 以“生态城市融合共生”为主题的第二届生态治理(南森)大会24日在北京召开。会上公布，候鸟迁飞通道国际科教联盟项目入选联合国教科文组织(UNESCO)“科学十年”。该项目由北京林业大学牵头，联合12个国家和地区的20所高校、科研机构共同参与，是全球首批25个入选“2024—2",
      "source_url": "http://www.chinanews.com/society.shtml",
      "category": "News"
    },
    {
      "title": "“笔趣阁”商标被判无效 专家：彰显中国打击盗版产业的决心",
      "link": "http://www.chinanews.com/sh/2025/10-24/10503983.shtml",
      "date": "2025-10-24 19:46",
      "author": "中新网社会新闻",
      "timestamp": 1761306411.0,
      "summary": "中新网北京10月24日电 (记者 应妮)北京市高级人民法院日前就“笔趣阁”商标无效宣告请求行政纠纷案作出终审判决。该案此前备受业界关注，因“笔趣阁”作为网络文学盗版网站长久以来对相关产业危害巨大。",
      "source_url": "http://www.chinanews.com/society.shtml",
      "category": "News"
    },
    {
      "title": "IBM称关键量子计算算法可在传统AMD芯片上运行",
      "link": "https://www.cnbeta.com.tw/articles/tech/1532678.htm",
      "date": "2025-10-24 19:44",
      "author": "cnBeta.COM.TW RSS订阅",
      "timestamp": 1761306272.0,
      "summary": "IBM公司周五表示，其一项关键量子计算算法能够在美国超微半导体公司（AMD）常规芯片上运行，这标志着超级计算机商业化又迈进一步。 阅读全文",
      "source_url": "https://www.cnbeta.com.tw",
      "category": "Blog"
    },
    {
      "title": "“一个都不能少”  浙江单村水站破解山村散户用水之困",
      "link": "http://www.chinanews.com/sh/2025/10-24/10503977.shtml",
      "date": "2025-10-24 19:44",
      "author": "中新网社会新闻",
      "timestamp": 1761306259.0,
      "summary": "中新网杭州10月24日电(鲍梦妮 葛芳妙)从浙江省丽水市景宁畲族自治县东坑镇出发，车子绕过一个个褶皱般起伏的山坳，大约又行驶了10分钟，73岁的何彭花的家映入眼帘。斑驳的外墙上，彩色喷漆留下一连串打井电话，一个、两个、三个……仿佛在诉说着山区“吃水难”的往事。",
      "source_url": "http://www.chinanews.com/society.shtml",
      "category": "News"
    },
    {
      "title": "千亿韩元负债!《跑跑卡丁车》新作失利 开发商破产",
      "link": "https://www.cnbeta.com.tw/articles/game/1532676.htm",
      "date": "2025-10-24 19:42",
      "author": "cnBeta.COM.TW RSS订阅",
      "timestamp": 1761306138.0,
      "summary": "韩国游戏巨头Nexon近日发布IR资料（投资者关系文件）宣布，已启动旗下开发子公司Nitro Studio的破产清算程序。Nitro Studio曾负责开发《跑跑卡丁车》IP的新作 《跑跑卡丁车：漂移》（KartRider: Drift）。 阅读全文",
      "source_url": "https://www.cnbeta.com.tw",
      "category": "Blog"
    },
    {
      "title": "Windows画图新增Restyle功能 AI生成不同艺术风格图片",
      "link": "https://www.cnbeta.com.tw/articles/tech/1532674.htm",
      "date": "2025-10-24 19:41",
      "author": "cnBeta.COM.TW RSS订阅",
      "timestamp": 1761306089.0,
      "summary": "随着生成式AI日渐渗透到Windows系统的各个角落，画图（Paint）应用也不例外。微软正在为Windows 11的画图添加一项全新的AI功能，名为Restyle，可以帮助用户轻松地将现有图像重新设计成各种艺术风格。 阅读全文",
      "source_url": "https://www.cnbeta.com.tw",
      "category": "Blog"
    },
    {
      "title": "特斯拉人形机器人再延期，消息称因为双手只能用六星期",
      "link": "https://www.ithome.com/0/892/195.htm",
      "date": "2025-10-24 19:40",
      "author": "IT之家",
      "timestamp": 1761306021.0,
      "summary": "IT之家 10 月 24 日消息，马斯克在昨天的第三季度电话会上确认，第三代人形机器人 Optimus 的设计定型将推迟到明年一季度。据晚点今日报道，一位特斯拉供应链人士透露，特斯拉原本计划在今年初确定三代机器人技术方案并开始量产，这家供应商能获得价值数亿美元的订单，为此他们已投入数亿元和数百人研发",
      "source_url": "https://www.ithome.com/",
      "category": "Blog"
    },
    {
      "title": "江苏扬州举办抗美援朝主题展 百余件展品致敬抗美援朝英烈",
      "link": "http://www.chinanews.com/sh/2025/10-24/10503965.shtml",
      "date": "2025-10-24 19:37",
      "author": "中新网社会新闻",
      "timestamp": 1761305830.0,
      "summary": "中新网扬州10月24日电 (朱晓颖 崔佳明)10月24日，在中国人民志愿军抗美援朝出国作战75周年纪念日即将到来之际，由扬州市档案馆、扬州市地方志办公室主办的“丰碑永铸薪火相传——纪念中国人民志愿军抗美援朝出国作战75周年主题展”在扬州市档案馆展出。",
      "source_url": "http://www.chinanews.com/society.shtml",
      "category": "News"
    },
    {
      "title": "新央企长安汽车：2025 年第三季度营收 422.36 亿元同比增长 23%，归母净利润 7.64 亿元",
      "link": "https://www.ithome.com/0/892/194.htm",
      "date": "2025-10-24 19:30",
      "author": "IT之家",
      "timestamp": 1761305433.0,
      "summary": "IT之家 10 月 24 日消息，长安汽车今日公告，2025 年第三季度实现营业收入 422.36 亿元，同比增长 23.36%；归属于上市公司股东的净利润 7.64 亿元，同比增长 2.13%；基本每股收益 0.08 元。累计来看，长安汽车前三季度实现营业收入 1149.27 亿元，同比增长 3.",
      "source_url": "https://www.ithome.com/",
      "category": "Blog"
    },
    {
      "title": "小米神秘穿戴设备入网，支持 UWB 技术",
      "link": "https://www.ithome.com/0/892/191.htm",
      "date": "2025-10-24 19:23",
      "author": "IT之家",
      "timestamp": 1761304982.0,
      "summary": "IT之家 10 月 24 日消息，一款型号为 M2542T1 的小米神秘穿戴设备于 10 月 21 日在工信部入网，支持 UWB 技术，目前尚不清楚这款新品的更多消息。值得一提的是，一款型号为 25128PNA1C 的小米新机 10 月 10 日通过工信部无线电核准，支持天通一号卫星通话、北斗短报文",
      "source_url": "https://www.ithome.com/",
      "category": "Blog"
    },
    {
      "title": "工信部：电动自行车充电桩新国标公开征求意见",
      "link": "https://www.ithome.com/0/892/190.htm",
      "date": "2025-10-24 19:14",
      "author": "IT之家",
      "timestamp": 1761304444.0,
      "summary": "IT之家 10 月 24 日消息，工信部官网今日发文，公开征求对《电动自行车充电桩安全技术规范》强制性国家标准（征求意见稿）的意见。IT之家从征求意见稿编制说明获悉，我国是电动自行车生产、消费大国，社会保有量约 3.8 亿辆，电动自行车已成为人民群众短途出行的重要交通工具。积极推进全国电动自行车安全",
      "source_url": "https://www.ithome.com/",
      "category": "Blog"
    },
    {
      "title": "文莱正式认可中国民航局适航标准，2023 年就已订购 20 亿美元商飞 C909 和 C919 客机",
      "link": "https://www.ithome.com/0/892/189.htm",
      "date": "2025-10-24 19:06",
      "author": "IT之家",
      "timestamp": 1761304005.0,
      "summary": "IT之家 10 月 24 日消息，新华社今日报道，文莱民航局发布了最新修订的民航法规，正式认可中国民用航空局（CAAC）的适航标准，并将其列为可接受的设计国适航当局。根据这项新规，在文莱进行航空器型号注册认证审批时，由中国民航局颁发的型号合格证文件可作为有效的型号设计批准证明。文莱骐骥航空首席执行官",
      "source_url": "https://www.ithome.com/",
      "category": "Blog"
    },
    {
      "title": "九号电动车凌波 OS 推送计划公布，首批 10 月 28 日起陆续推送",
      "link": "https://www.ithome.com/0/892/188.htm",
      "date": "2025-10-24 19:02",
      "author": "IT之家",
      "timestamp": 1761303749.0,
      "summary": "IT之家 10 月 24 日消息，九号电动今日公布了凌波 OS 推送计划，该系统将于 10 月 28 日起陆续推送。九号短途交通全域操作系统凌波 OS 于今年 8 月发布，支持多设备端协同、智能配件联动等特性，可打破设备边界，提供智能服务，将覆盖九号全品类产品，可支撑整车全域控制单元。IT之家整理九",
      "source_url": "https://www.ithome.com/",
      "category": "Blog"
    },
    {
      "title": "欧盟指控Meta与TikTok违反数字法规",
      "link": "https://www.cnbeta.com.tw/articles/tech/1532672.htm",
      "date": "2025-10-24 18:53",
      "author": "cnBeta.COM.TW RSS订阅",
      "timestamp": 1761303220.0,
      "summary": "欧盟委员会周五指控Meta公司及TikTok违反了欧盟的标志性社交媒体规定。欧盟执行部门表示，Meta旗下的Facebook和Instagram，以及TikTok均未能履行其向研究人员开放平台数据的义务。同时，Facebook和Instagram还被认为在帮助用户举报非法内容及对内容审核决定提出申诉",
      "source_url": "https://www.cnbeta.com.tw",
      "category": "Blog"
    },
    {
      "title": "今年第三烧 53万的理想MEGA自燃，炸出了奶爸宝妈的焦虑",
      "link": "https://www.cnbeta.com.tw/articles/tech/1532670.htm",
      "date": "2025-10-24 18:46",
      "author": "cnBeta.COM.TW RSS订阅",
      "timestamp": 1761302777.0,
      "summary": "在汽车圈有一句广为话：安全才是最大的豪华。但一辆起售价52.98万的豪华纯电汽车——理想MEGA，昨晚竟再度发生起火事故。尽管理想MEGA一经亮相就备受争议：喜欢它的人称之为&quot;最舒服的MPV&quot;；不喜欢它的人则看都不会看一眼。这种两极分化的口碑，让它始终话题度居高不下。 阅读全文",
      "source_url": "https://www.cnbeta.com.tw",
      "category": "Blog"
    },
    {
      "title": "宗馥莉两大“心腹”岗位变更：严学峰恢复生产总监职位 祝丽丹仍“待定”",
      "link": "https://www.cnbeta.com.tw/articles/tech/1532668.htm",
      "date": "2025-10-24 18:45",
      "author": "cnBeta.COM.TW RSS订阅",
      "timestamp": 1761302744.0,
      "summary": "10月24日，宏胜饮料集团有限公司内部系统中，严学峰的岗位显示已由“待定”恢复为“生产中心总监兼迅尔公司总经理”。同期被传离职的宏胜集团另一核心人物祝丽丹，岗位仍为“待定”。 阅读全文",
      "source_url": "https://www.cnbeta.com.tw",
      "category": "Blog"
    },
    {
      "title": "CS饰品崩盘 大学生崩溃",
      "link": "https://www.cnbeta.com.tw/articles/game/1532666.htm",
      "date": "2025-10-24 18:44",
      "author": "cnBeta.COM.TW RSS订阅",
      "timestamp": 1761302686.0,
      "summary": "《反恐精英2》近日推出重大更新，扩展了汰换合同系统。玩家如今可以通过使用5件隐秘级皮肤，合成出一把稀有刀具或手套——这一功能在游戏历史上尚属首次。 阅读全文",
      "source_url": "https://www.cnbeta.com.tw",
      "category": "Blog"
    },
    {
      "title": "苹果M5单核性能逆天 AMD、Intel、高通都看不见尾灯",
      "link": "https://www.cnbeta.com.tw/articles/tech/1532664.htm",
      "date": "2025-10-24 18:43",
      "author": "cnBeta.COM.TW RSS订阅",
      "timestamp": 1761302638.0,
      "summary": "无论A系列还是M系列，苹果处理器一直以遥遥领先的单核性能而著称，根本没有敌手，最新发布的M5同样如此。贴吧网友“NPacific”使用CPU-Z ARM64版本，在Windows 11系统下测试了苹果M5的单核、多核性能。 阅读全文",
      "source_url": "https://www.cnbeta.com.tw",
      "category": "Blog"
    },
    {
      "title": "文莱批准运营中国大飞机：两年前就买了20亿美元的C909、C919",
      "link": "https://www.cnbeta.com.tw/articles/tech/1532662.htm",
      "date": "2025-10-24 18:43",
      "author": "cnBeta.COM.TW RSS订阅",
      "timestamp": 1761302609.0,
      "summary": "文莱民航局发布的新条例显示，文莱航空公司已经获准运营中国制造的客机。其实早在2023年，文莱骐骥航空从中国商飞订购了C909、C919客机。 阅读全文",
      "source_url": "https://www.cnbeta.com.tw",
      "category": "Blog"
    },
    {
      "title": "世界卫生组织指出抗微生物耐药性已成为全球公共卫生的重大威胁",
      "link": "https://www.cnbeta.com.tw/articles/tech/1532660.htm",
      "date": "2025-10-24 18:43",
      "author": "cnBeta.COM.TW RSS订阅",
      "timestamp": 1761302585.0,
      "summary": "世界卫生组织（WHO）发布最新《全球抗生素耐药性监测报告》，指出抗微生物耐药性（AMR）已成为全球公共卫生的重大威胁。在许多常见感染和常规医疗操作中，耐药性持续削弱救命治疗的有效性，令全球人口面临更高风险。 阅读全文",
      "source_url": "https://www.cnbeta.com.tw",
      "category": "Blog"
    },
    {
      "title": "蓝牙技术联盟宣布成立中国兴趣小组，华为、小米、OPPO、荣耀、联想等参会",
      "link": "https://www.ithome.com/0/892/185.htm",
      "date": "2025-10-24 18:41",
      "author": "IT之家",
      "timestamp": 1761302519.0,
      "summary": "IT之家 10 月 24 日消息，蓝牙技术联盟今日宣布成立中国兴趣小组，该小组面向所有创始成员（Promoter member）和联盟成员（Associate member）企业开放，致力于打造一个协作、教育与市场拓展的平台，确保中国市场的独特需求与发展机遇在全球蓝牙技术联盟生态中得到充分体现与积极",
      "source_url": "https://www.ithome.com/",
      "category": "Blog"
    },
    {
      "title": "新冷空气又“续”上了！北方将冷上加冷局地降温超8℃",
      "link": "http://www.chinanews.com/sh/2025/10-24/10503945.shtml",
      "date": "2025-10-24 18:40",
      "author": "中新网社会新闻",
      "timestamp": 1761302457.0,
      "summary": "今天早晨，北方“冷气”依旧很足，东北地区可以说是冻感十足，气温均跌破冰点。其中哈尔滨最低气温零下5.5℃、长春零下7.1℃，均刷新了下半年来新低。此时已进入冷空气的主场，这不，新一股冷空气又要上线。",
      "source_url": "http://www.chinanews.com/society.shtml",
      "category": "News"
    },
    {
      "title": "马云现身宁波与好友惬意聚餐：在一家中式酒馆喝酒 脸色发红",
      "link": "https://www.cnbeta.com.tw/articles/tech/1532658.htm",
      "date": "2025-10-24 18:39",
      "author": "cnBeta.COM.TW RSS订阅",
      "timestamp": 1761302397.0,
      "summary": "近日，阿里巴巴创始人马云又出现在了公众视野中。有网友在社交平台晒出照片，称马云现身宁波的一家中式酒馆“三佰杯”，跟好友们在一起喝美酒、品尝美食。 阅读全文",
      "source_url": "https://www.cnbeta.com.tw",
      "category": "Blog"
    },
    {
      "title": "微软Edge浏览器“Copilot模式”为浏览标签页带来更多AI功能",
      "link": "https://www.cnbeta.com.tw/articles/tech/1532656.htm",
      "date": "2025-10-24 18:37",
      "author": "cnBeta.COM.TW RSS订阅",
      "timestamp": 1761302244.0,
      "summary": "微软近日为其Edge浏览器的AI“Copilot模式”推出了新功能，紧随其他竞品浏览器的一系列AI新举措。“Copilot模式”最早于今年7月公布，通过在每个Edge标签页中引入聊天界面，允许用户直接提问、检索信息或输入网址。值得注意的是，该模式可以同时分析所有打开的标签页内容，使用户能够方便地对比",
      "source_url": "https://www.cnbeta.com.tw",
      "category": "Blog"
    },
    {
      "title": "工信部：截至 9 月末 5G 基站总数 470.5 万个，5G 移动电话用户 11.67 亿户",
      "link": "https://www.ithome.com/0/892/183.htm",
      "date": "2025-10-24 18:36",
      "author": "IT之家",
      "timestamp": 1761302167.0,
      "summary": "IT之家 10 月 24 日消息，工信部今日发布 2025 年前三季度通信业经济运行情况，前三季度，电信业务收入累计完成 13270 亿元，同比增长 0.9%。按照上年不变价计算的电信业务总量同比增长 9%。截至 9 月末，三家基础电信企业及中国广电的移动电话用户总数达 18.28 亿户，比上年末净",
      "source_url": "https://www.ithome.com/",
      "category": "Blog"
    },
    {
      "title": "沐曦股份科创板IPO获上市委会议审议通过",
      "link": "https://www.cnbeta.com.tw/articles/tech/1532654.htm",
      "date": "2025-10-24 18:34",
      "author": "cnBeta.COM.TW RSS订阅",
      "timestamp": 1761302062.0,
      "summary": "国产GPU厂商沐曦股份科创板IPO获上市委会议审议通过。公司IPO拟融资39.04亿元，用于投资“新型高性能通用GPU研发及产业化项目”、“新一代人工智能推理GPU研发及产业化项目”和“面向前沿领域及新兴应用场景的高性能GPU技术研发项目”。 阅读全文",
      "source_url": "https://www.cnbeta.com.tw",
      "category": "Blog"
    },
    {
      "title": "娃哈哈经销商称明年保证金收紧：负增长部分需按1.5倍追加",
      "link": "https://www.cnbeta.com.tw/articles/tech/1532652.htm",
      "date": "2025-10-24 18:32",
      "author": "cnBeta.COM.TW RSS订阅",
      "timestamp": 1761301945.0,
      "summary": "昨晚，有消息称宗馥莉所控股的宏胜系下发通知，2026年将继续使用“娃哈哈”品牌。今日，有娃哈哈经销商表示，宏胜集团近期在销售会议中发布核心事项通知，对经销商合作门槛与回款要求作出明确收紧调整。 阅读全文",
      "source_url": "https://www.cnbeta.com.tw",
      "category": "Blog"
    },
    {
      "title": "2025全国秋冬进程：华北“跑步”入冬 你那儿秋天“缩水”了吗？",
      "link": "http://www.chinanews.com/sh/2025/10-24/10503934.shtml",
      "date": "2025-10-24 18:03",
      "author": "中新网社会新闻",
      "timestamp": 1761300191.0,
      "summary": "中国天气网讯 “前天短袖、昨天薄外套、今天羽绒服……”这个画面或许是今年秋冬天不少人经历的“换季快闪”的真实写照。华北秋季“闪现”、“跑步”入冬，江南则秋老虎不退、入秋姗姗来迟，最近我国多地季节转换节奏不同寻常。中国天气网推出2025年秋冬进程图，还有秋日数据大盘点，看看你家是“冬来早”还是“秋来迟",
      "source_url": "http://www.chinanews.com/society.shtml",
      "category": "News"
    },
    {
      "title": "氪星晚报｜淘宝出海正式上线跨境家具直邮服务；Rivian计划裁员超600人；雷军回应小米K90定价",
      "link": "https://36kr.com/p/3523010061130631?f=rss",
      "date": "2025-10-24 18:01",
      "author": "36氪",
      "timestamp": 1761300064.0,
      "summary": "大公司：\n  Rivian计划裁员超600人\n  在特朗普政府调整法规的背景下，Rivian及其他电动汽车制造商正面临愈发严峻的市场环境。据报道，全电动汽车制造商Rivian汽车公司计划裁员逾600人，目前该公司正面临日益严峻的市场挑战。\n  娃哈哈经销商接通知：明年卖娃哈哈不卖娃小宗\n  宗馥莉辞",
      "source_url": "http://36kr.com",
      "category": "Blog"
    },
    {
      "title": "贵州绥阳双河洞长度刷新至439.7公里",
      "link": "http://www.chinanews.com/sh/2025/10-24/10503927.shtml",
      "date": "2025-10-24 18:00",
      "author": "中新网社会新闻",
      "timestamp": 1761300055.0,
      "summary": "中新社贵州绥阳10月24日电 (记者 瞿宏伦 袁超)亚洲第一长洞——双河洞连通长度刷新至439.7公里，继续稳居世界第三、亚洲第一长洞，纵深仍保持中国第三。",
      "source_url": "http://www.chinanews.com/society.shtml",
      "category": "News"
    },
    {
      "title": "前小米高管创业，融资近2亿元，要做AI影像消费硬件丨智能涌现独家",
      "link": "https://36kr.com/p/3522981563931525?f=rss",
      "date": "2025-10-24 17:23",
      "author": "36氪",
      "timestamp": 1761297839.0,
      "summary": "文｜邓咏仪\n  编辑｜苏建勋\n  在小米工作的11年，从一线员工做到管理层，马骥“创业”过不止一次。\n  曾经作为小米管理层的年轻一代，马骥负责过MIUI系统，到统领小米全球互联网业务及商业化，再到中国区建设小米新零售体系和小米网。横跨软件、硬件以及不同部门和岗位，这让马骥被公认为“能打硬仗”的一位",
      "source_url": "http://36kr.com",
      "category": "Blog"
    },
    {
      "title": "研发投入超百亿，还挤不进这个行业科创TOP10？| 2025行业科创解读（一）",
      "link": "https://www.infzm.com/contents/305639",
      "date": "2025-10-24 17:07",
      "author": "南方周末-新闻",
      "timestamp": 1761296867.0,
      "summary": "编者按：\n                        地缘政治冲突不断，行业竞争螺旋升级。\n在“不科创，无未来”的紧迫感中，中国企业一面加大研发投入，力争上游；一面加大对科创的传播和营销，对其科创活动和表现各有表述。从行业看，各家企业的科创力和科",
      "source_url": "https://www.infzm.com/contents?term_id=2",
      "category": "News"
    },
    {
      "title": "还有人敢报考外语专业翻译专业吗？",
      "link": "http://www.huxiu.com/article/4795494.html?f=wangzhan",
      "date": "2025-10-24 17:00",
      "author": "虎嗅网",
      "timestamp": 1761296400.0,
      "summary": "从最赚钱的专业到顶级学院关门，翻译专业真的被AI给干掉了吗？那问题来了，翻译行业的衰落和AI关系大吗？这期视频我们就来聊聊这个话题。下载虎嗅APP，第一时间获取深度独到的商业科技资讯，连接更多创新人群与线下活动",
      "source_url": "http://www.huxiu.com",
      "category": "Blog"
    },
    {
      "title": "逐梦岭南，相约十五运",
      "link": "https://www.infzm.com/contents/295341",
      "date": "2025-10-24 16:13",
      "author": "南方周末-新闻",
      "timestamp": 1761293588.0,
      "summary": "",
      "source_url": "https://www.infzm.com/contents?term_id=2",
      "category": "News"
    },
    {
      "title": "中国光学的下一个故事，从孩子的书桌上开始",
      "link": "https://36kr.com/p/3522903860943748?f=rss",
      "date": "2025-10-24 16:05",
      "author": "36氪",
      "timestamp": 1761293150.0,
      "summary": "在科技世界里，真正令人敬佩的，不只是那些颠覆想象的发明，还有愿意让技术回归初心的人。\n  詹姆斯·戴森（James&nbsp;Dyson）便是这样一位工程师型科学家。上世纪八十年代，他发明了世界上第一台无尘袋吸尘器。戴森没有让这项技术停留在工业领域，而是将其带入了普通家庭生活。那些曾经埋藏在实验室里",
      "source_url": "http://36kr.com",
      "category": "Blog"
    },
    {
      "title": "NASA欧罗巴快船探测器准备绕到星际彗星3I/ATLAS后方收集离子尾物质进行分析",
      "link": "https://www.landiannews.com/archives/110992.html",
      "date": "2025-10-24 15:26",
      "author": "蓝点网",
      "timestamp": 1761290797.0,
      "summary": "#太空探索 NASA 欧罗巴快船号探测器准备绕到星际彗星 3I/ATLAS 后收集离子尾物质进行分析，不过由于美国政府停摆，能否及时启动科学仪器还是个问题。3I/ATLAS 来自星际空间，此前人类还没有直接采集到过来自星际空间的物质，所以这是个千载难逢的好机会。查看全文：https://ourl.c",
      "source_url": "https://www.landiannews.com",
      "category": "Blog"
    },
    {
      "title": "调查人员在泰坦尼克号潜水器残骸中发现保存完好的闪迪SD卡 可惜里面没事故数据",
      "link": "https://www.landiannews.com/archives/110991.html",
      "date": "2025-10-24 15:09",
      "author": "蓝点网",
      "timestamp": 1761289772.0,
      "summary": "#生活周边 调查人员在海洋之门残骸 (泰坦尼克号观光潜水器) 中发现保存完好的闪迪 SD 卡，可惜里面没有事故发生时的画面。调查人员确实恢复了 12 张图像和 9 段视频，但这台海底相机存储被设置为机载存储而非 SD 卡，导致 SD 卡里没有拍到任何事故发生时的视频。查看全文：https://our",
      "source_url": "https://www.landiannews.com",
      "category": "Blog"
    },
    {
      "title": "苹果因应用商店抽成在英国被起诉且已经败诉 法院要求苹果支付20亿美元罚款",
      "link": "https://www.landiannews.com/archives/110990.html",
      "date": "2025-10-24 14:36",
      "author": "蓝点网",
      "timestamp": 1761287761.0,
      "summary": "#科技资讯 苹果因应用商店抽成问题在英国被起诉且已经败诉，法院要求苹果支付大约 15 亿英镑 (约合 20 亿美元) 的罚款。这仅仅只是罚款，法院还准备举办听证会确定苹果应该向英国开发者们支付多少赔偿金，不过苹果表示将提起上诉。查看全文：https://ourl.co/110990",
      "source_url": "https://www.landiannews.com",
      "category": "Blog"
    },
    {
      "title": "房企“一哥”保利发展拿地猛降6成，三季度盈利首现亏损",
      "link": "https://36kr.com/p/3522740183030920?f=rss",
      "date": "2025-10-24 13:17",
      "author": "36氪",
      "timestamp": 1761283077.0,
      "summary": "5个月前，保利发展还在凶猛拿地，上海、北京等核心市场上均有所斩获，但进入今年第三季度之后，保利的拿地速度明显减缓了。\n  据中指研究院统计，今年上半年，保利发展以414亿元的权益拿地金额排名行业第一，平均每月耗资69亿元。但是到了9月底，保利发展的拿地金额只增长到了490亿元，下滑到了行业第五，被中",
      "source_url": "http://36kr.com",
      "category": "Blog"
    },
    {
      "title": "豆包大模型上车赛力斯自有品牌｜36氪独家",
      "link": "https://36kr.com/p/3423694660275841?f=rss",
      "date": "2025-10-24 13:06",
      "author": "36氪",
      "timestamp": 1761282418.0,
      "summary": "字节跳动旗下的火山引擎，和赛力斯布在具身智能领域达成合作之后，36氪了解到，双方也在合作推动豆包大模型进入车机。\n  这一合作项目，现已在研发阶段。\n  字节的AI产品豆包家族，是目前国内用户规模最大的AI原生应用之一，因而在二者的合作中，赛力斯负责车机系统架构研发，火山则专注于大模型在车端的应用部",
      "source_url": "http://36kr.com",
      "category": "Blog"
    },
    {
      "title": "36氪首发｜「UMe Tea优米茶铺」完成1000万美元A轮融资，华人工程师在北美开奶茶店",
      "link": "https://36kr.com/p/3521277005896841?f=rss",
      "date": "2025-10-24 12:34",
      "author": "36氪",
      "timestamp": 1761280473.0,
      "summary": "36氪获悉，北美茶饮品牌「UMe Tea优米茶铺」近日完成1000万美元A轮融资，由美国本土基金Conductive Ventures领投，iFly.vc、EGP（明裕创投）跟投，本轮资金将重点用于团队完善、湾区门店加密等。\n  「UMe Tea优米茶铺」（下称“UMe Tea”）是36氪持续关注的",
      "source_url": "http://36kr.com",
      "category": "Blog"
    },
    {
      "title": "114亿美元交易背后的野心，没换来股价上涨",
      "link": "https://36kr.com/p/3521459482532739?f=rss",
      "date": "2025-10-24 12:26",
      "author": "36氪",
      "timestamp": 1761279985.0,
      "summary": "文｜胡香赟\n  编辑｜海若镜\n  10月以来，创新药股市出现下滑走势，就在行业都调侃着“再来个大交易提振下信心”时，“大交易”真的来了。\n  10月22日，信达生物宣布与武田制药达成总价114亿美元的授权合作，包括12亿美元首付款和102亿美元的潜在里程碑付款，其中，首付款中含有武田制药溢价20%入",
      "source_url": "http://36kr.com",
      "category": "Blog"
    },
    {
      "title": "Z世代家电消费升级，品质健康引领技术｜世研消费指数品牌榜Vol.79",
      "link": "https://36kr.com/p/3521575690198148?f=rss",
      "date": "2025-10-24 12:00",
      "author": "36氪",
      "timestamp": 1761278400.0,
      "summary": "本次监测周期内，石头科技、统帅和华凌分别以1.85、1.66和1.47的综合热度指数位列榜单Top3。\n  \n  图源：世研大消费指数\n  Z世代家电消费升级需求显现，精准分层策略助推子品牌差异化增长\n  从上榜品牌来看，统帅与华凌在本月表现强势，共同印证了家电市场年轻化与精准分层策略的成功。",
      "source_url": "http://36kr.com",
      "category": "Blog"
    },
    {
      "title": "特斯拉向下，比亚迪向上",
      "link": "http://www.huxiu.com/article/4796284.html?f=wangzhan",
      "date": "2025-10-24 11:02",
      "author": "虎嗅网",
      "timestamp": 1761274925.0,
      "summary": "本文来自微信公众号：定焦One，作者：金玙璠，编辑：魏佳，题图来自：AI生成10月，新能源汽车界的两大“顶流”——特斯拉和比亚迪，都交出了一份“看似亮眼、实则隐忧”的答卷。先来看看那个总能搅动风云的特斯拉。北京时间10月23日美股盘后，特斯拉公布了2025年第三季度财报：因为季度交付量（49.7万",
      "source_url": "http://www.huxiu.com",
      "category": "Blog"
    },
    {
      "title": "美国初创公司计划将英伟达H100加速器发射到太空 利用太阳能供电和宇宙低温提高效率",
      "link": "https://www.landiannews.com/archives/110989.html",
      "date": "2025-10-24 10:45",
      "author": "蓝点网",
      "timestamp": 1761273930.0,
      "summary": "#人工智能 美国初创公司 Starcloud 计划将英伟达 H100 GPU 发射到太空运行，利用太阳能供电和宇宙极低的温度进行散热。在太空供电可能不是问题，但宇宙真空环境只能靠辐射散热，辐射散热效率极低因此需要配备巨大的散热板，当然出现故障了也没法维修，如果无法远程解决问题那卫星和芯片都要变成太空",
      "source_url": "https://www.landiannews.com",
      "category": "Blog"
    },
    {
      "title": "惊天反转：辞职41天，宗馥莉重新启用「娃哈哈」| 深氪",
      "link": "https://36kr.com/p/3522581139233669?f=rss",
      "date": "2025-10-24 10:40",
      "author": "36氪",
      "timestamp": 1761273659.0,
      "summary": "文｜钟艺璇\n  编辑｜杨轩 乔芊\n  封面来源｜视觉中国\n  重回谈判桌\n  娃哈哈内部博弈，又出现巨大反转。\n  36氪从两个独立信源独家获悉，宗馥莉所控股的宏胜系10月23日傍晚下发通知，2026年将继续使用“娃哈哈”品牌。这意味着，宗馥莉宣称要做的“娃小宗”，只存在了41天。\n  截止发稿前，",
      "source_url": "http://36kr.com",
      "category": "Blog"
    },
    {
      "title": "企业变革，要不要平衡利益？",
      "link": "http://www.huxiu.com/article/4795855.html?f=wangzhan",
      "date": "2025-10-24 10:35",
      "author": "虎嗅网",
      "timestamp": 1761273339.0,
      "summary": "宗馥莉在娃哈哈包括数字化、流程化的系列改革，引发争议。有人认为宗馥莉的改革，没有考虑内部毅力的平衡。那么宗馥莉的改革是成功的吗？企业变革要不要考虑利益平衡？下载虎嗅APP，第一时间获取深度独到的商业科技资讯，连接更多创新人群与线下活动",
      "source_url": "http://www.huxiu.com",
      "category": "Blog"
    },
    {
      "title": "不装人的它，为何能一把融6亿美金？",
      "link": "http://www.huxiu.com/article/4796204.html?f=wangzhan",
      "date": "2025-10-24 10:32",
      "author": "虎嗅网",
      "timestamp": 1761273159.0,
      "summary": "出品丨虎嗅汽车组作者丨李赓&nbsp;头图丨视觉中国单轮次6亿美金，刷新了自动驾驶赛道（L4）融资记录。不过这次不再是载人出行（RoboTaxi），而是城市物流（RoboVan）。10月23日，中国也是全球的L4级无人城配龙头公司，新石器公司（Neolix）正式宣布完成逾6亿美元D轮融资。以金额计",
      "source_url": "http://www.huxiu.com",
      "category": "Blog"
    },
    {
      "title": "当生活出现BUG，你会暂时跑向哪里？丨「1024」特别策划",
      "link": "https://36kr.com/p/3522563239779463?f=rss",
      "date": "2025-10-24 10:27",
      "author": "36氪",
      "timestamp": 1761272853.0,
      "summary": "&amp;amp;nbsp;\n  \n  \n  \n  \n  \n  \n  \n  \n  \n  \n  \n  \n  \n  \n  &nbsp;",
      "source_url": "http://36kr.com",
      "category": "Blog"
    },
    {
      "title": "Ubuntu 25.10版附带的组件导致自动更新中断 用户可以手动运行命令继续更新",
      "link": "https://www.landiannews.com/archives/110988.html",
      "date": "2025-10-24 10:21",
      "author": "蓝点网",
      "timestamp": 1761272471.0,
      "summary": "#系统资讯 Ubuntu 25.10 版附带的基于 Rust 的 uutils 组件存在故障导致系统无法自动检测软件更新，用户可以手动运行命令继续更新。这个错误影响 0.2.2-0ubuntu2.1 之前的版本，用户需要手动运行 apt 命令更新版本，更新后就可以恢复自动检查更新，不更新的话系统永远",
      "source_url": "https://www.landiannews.com",
      "category": "Blog"
    },
    {
      "title": "卖爆了的特斯拉，赚不到钱了？",
      "link": "http://www.huxiu.com/article/4796158.html?f=wangzhan",
      "date": "2025-10-24 10:00",
      "author": "虎嗅网",
      "timestamp": 1761271238.0,
      "summary": "特斯拉又卖爆了，可马斯克却高兴不起来。三季度销量创新高，储能产品激增81%，公司利润却大幅下滑，净利润骤降37%，毛利率连20%都回不去了。下载虎嗅APP，第一时间获取深度独到的商业科技资讯，连接更多创新人群与线下活动",
      "source_url": "http://www.huxiu.com",
      "category": "Blog"
    },
    {
      "title": "亚马逊公布AWS重大故障调查结果：内部关键软件错误和自动化系统打架引起的联级问题",
      "link": "https://www.landiannews.com/archives/110987.html",
      "date": "2025-10-24 09:59",
      "author": "蓝点网",
      "timestamp": 1761271169.0,
      "summary": "#云计算 亚马逊 AWS 公布早前重大故障的调查结果：内部关键软件错误和自动化系统打架引起的联级问题。出现问题的主要是 DynamoDB DNS 两个组件，这些组件存在竞争条件导致删除关键网络条目从而引发了多米诺效应，现在亚马逊已经暂停两个自动化系统。查看全文：https://ourl.co/110",
      "source_url": "https://www.landiannews.com",
      "category": "Blog"
    },
    {
      "title": "特朗普赦免币安创始人赵长鹏 特朗普称与很多犯罪相比赵长鹏的事儿都不叫犯罪",
      "link": "https://www.landiannews.com/archives/110986.html",
      "date": "2025-10-24 09:39",
      "author": "蓝点网",
      "timestamp": 1761269961.0,
      "summary": "#加密货币 特朗普使用美国宪法赋予的总统特权赦免币安创始人赵长鹏，特朗普称与很多犯罪相比赵长鹏的事儿都不叫犯罪。目前特朗普已经赦免很多加密货币相关的犯罪者，而赵长鹏被赦免后预计将为他和币安重返美国市场铺平道路，这项赦免也将终止美国司法部对币安的监控。查看全文：https://ourl.co/1109",
      "source_url": "https://www.landiannews.com",
      "category": "Blog"
    },
    {
      "title": "苹果介绍AirPods新功能：佩戴耳机睡着后系统将自动暂停播放音视频内容",
      "link": "https://www.landiannews.com/archives/110985.html",
      "date": "2025-10-24 09:23",
      "author": "蓝点网",
      "timestamp": 1761269033.0,
      "summary": "#手机数码 苹果介绍 AirPods 的新功能：佩戴耳机睡着时系统将自动暂停播放音视频内容帮助用户放松身心准备入睡。该功能默认情况下是关闭的，用户佩戴 AirPods 后可以在设置里主动开启入睡时暂停媒体，这样当传感器检测到用户可能睡着后就会暂停播放。查看全文：https://ourl.co/110",
      "source_url": "https://www.landiannews.com",
      "category": "Blog"
    },
    {
      "title": "巴阿边境冲突，或涉金新月地区的毒品生意博弈丨军事",
      "link": "https://www.infzm.com/contents/305144",
      "date": "2025-10-24 09:00",
      "author": "南方周末-新闻",
      "timestamp": 1761267600.0,
      "summary": "（本文首发于南方人物周刊）\n                \n                \n                                        南方人物周刊特约撰稿 朱江明",
      "source_url": "https://www.infzm.com/contents?term_id=2",
      "category": "News"
    },
    {
      "title": "印度航母：依旧用最不靠谱的方式，表达最坚定的自信",
      "link": "http://www.huxiu.com/article/4795140.html?f=wangzhan",
      "date": "2025-10-24 08:00",
      "author": "虎嗅网",
      "timestamp": 1761264000.0,
      "summary": "印度航母——航母怎么能少了歌舞和瑜伽，这么多年以来，印度依旧用最不靠谱的方式表达最坚定的自信......下载虎嗅APP，第一时间获取深度独到的商业科技资讯，连接更多创新人群与线下活动",
      "source_url": "http://www.huxiu.com",
      "category": "Blog"
    },
    {
      "title": "狂卖85座万达广场，王健林还是没等来救赎？",
      "link": "http://www.huxiu.com/article/4795924.html?f=wangzhan",
      "date": "2025-10-24 07:30",
      "author": "虎嗅网",
      "timestamp": 1761262200.0,
      "summary": "王健林，那个曾说“先挣他一个亿”的首富，如今身家一年蒸发820多亿，机场近照瘦成皮包骨，今天就来聊聊背后的故事。下载虎嗅APP，第一时间获取深度独到的商业科技资讯，连接更多创新人群与线下活动",
      "source_url": "http://www.huxiu.com",
      "category": "Blog"
    }
  ]
}